[
    {
        "RShoulderPitch": 76.81905683953657,
        "RShoulderRoll": -28.79359381234157,
        "RElbowRoll": 33.919255448419875,
        "RElbowYaw": 0,
        "LShoulderPitch": 79.17272015434932,
        "LShoulderRoll": 39.33092256904608,
        "LElbowRoll": 35.62767811856153,
        "LElbowYaw": 113.92320378456405
    },
    {
        "RShoulderPitch": 76.8439465189432,
        "RShoulderRoll": -28.778471540572003,
        "RElbowRoll": 33.963522696247026,
        "RElbowYaw": 0,
        "LShoulderPitch": 79.19948911218536,
        "LShoulderRoll": 39.37648499616369,
        "LElbowRoll": 35.668043140891854,
        "LElbowYaw": 114.02373648031801
    },
    {
        "RShoulderPitch": 76.8439465189432,
        "RShoulderRoll": -28.778471540572003,
        "RElbowRoll": 33.963522696247026,
        "RElbowYaw": 0,
        "LShoulderPitch": 79.19948911218536,
        "LShoulderRoll": 39.37648499616369,
        "LElbowRoll": 35.668043140891854,
        "LElbowYaw": 114.02373648031801
    },
    {
        "RShoulderPitch": 76.8439465189432,
        "RShoulderRoll": -28.778471540572003,
        "RElbowRoll": 33.963522696247026,
        "RElbowYaw": 0,
        "LShoulderPitch": 79.19948911218536,
        "LShoulderRoll": 39.37648499616369,
        "LElbowRoll": 35.668043140891854,
        "LElbowYaw": 114.02373648031801
    },
    {
        "RShoulderPitch": 76.8439465189432,
        "RShoulderRoll": -28.778471540572003,
        "RElbowRoll": 33.963522696247026,
        "RElbowYaw": 0,
        "LShoulderPitch": 79.19948911218536,
        "LShoulderRoll": 39.37648499616369,
        "LElbowRoll": 35.668043140891854,
        "LElbowYaw": 114.02373648031801
    },
    {
        "RShoulderPitch": 76.8439465189432,
        "RShoulderRoll": -28.778471540572003,
        "RElbowRoll": 33.963522696247026,
        "RElbowYaw": 0,
        "LShoulderPitch": 79.19948911218536,
        "LShoulderRoll": 39.37648499616369,
        "LElbowRoll": 35.668043140891854,
        "LElbowYaw": 114.02373648031801
    },
    {
        "RShoulderPitch": 76.82111229938229,
        "RShoulderRoll": -28.905215022111364,
        "RElbowRoll": 34.25200379438277,
        "RElbowYaw": 0,
        "LShoulderPitch": 79.11712898766005,
        "LShoulderRoll": 39.43664462796869,
        "LElbowRoll": 35.987425594768865,
        "LElbowYaw": 114.3696204109788
    },
    {
        "RShoulderPitch": 76.80606160756706,
        "RShoulderRoll": -28.904761437499793,
        "RElbowRoll": 35.03832645017994,
        "RElbowYaw": 0,
        "LShoulderPitch": 78.95599791759643,
        "LShoulderRoll": 39.46175214411972,
        "LElbowRoll": 36.29869466214785,
        "LElbowYaw": 114.55152607750239
    },
    {
        "RShoulderPitch": 76.60342156129754,
        "RShoulderRoll": -28.86455845366607,
        "RElbowRoll": 35.33355239746837,
        "RElbowYaw": 0,
        "LShoulderPitch": 78.80075759298664,
        "LShoulderRoll": 39.49109349888393,
        "LElbowRoll": 36.78616164632692,
        "LElbowYaw": 114.93885981939921
    },
    {
        "RShoulderPitch": 76.05984018885377,
        "RShoulderRoll": -29.131499649017442,
        "RElbowRoll": 37.347311153287535,
        "RElbowYaw": 0,
        "LShoulderPitch": 77.82140529414731,
        "LShoulderRoll": 39.31031121002169,
        "LElbowRoll": 37.53874611879789,
        "LElbowYaw": 115.99846851537112
    },
    {
        "RShoulderPitch": 76.05984018885377,
        "RShoulderRoll": -29.131499649017442,
        "RElbowRoll": 37.347311153287535,
        "RElbowYaw": 0,
        "LShoulderPitch": 77.82140529414731,
        "LShoulderRoll": 39.31031121002169,
        "LElbowRoll": 37.53874611879789,
        "LElbowYaw": 115.99846851537112
    },
    {
        "RShoulderPitch": 73.40092669898819,
        "RShoulderRoll": -30.257212057599826,
        "RElbowRoll": 36.851828219840485,
        "RElbowYaw": 0,
        "LShoulderPitch": 76.16695935041449,
        "LShoulderRoll": 39.46274498832635,
        "LElbowRoll": 39.017714846955215,
        "LElbowYaw": 0
    },
    {
        "RShoulderPitch": 71.61502280852977,
        "RShoulderRoll": -31.55726387671406,
        "RElbowRoll": 37.66890026074313,
        "RElbowYaw": 0,
        "LShoulderPitch": 74.760272828421,
        "LShoulderRoll": 39.57899026632054,
        "LElbowRoll": 40.07580601194465,
        "LElbowYaw": 0
    },
    {
        "RShoulderPitch": 69.82532710817178,
        "RShoulderRoll": -32.450322354653,
        "RElbowRoll": 37.67294287150219,
        "RElbowYaw": 0,
        "LShoulderPitch": 73.88615097105956,
        "LShoulderRoll": 39.92994438258948,
        "LElbowRoll": 41.46720307184458,
        "LElbowYaw": 0
    },
    {
        "RShoulderPitch": 68.76589095109352,
        "RShoulderRoll": -33.688051372424695,
        "RElbowRoll": 39.909077584451296,
        "RElbowYaw": 0,
        "LShoulderPitch": 72.92280867170602,
        "LShoulderRoll": 40.00811077169965,
        "LElbowRoll": 42.14288233741303,
        "LElbowYaw": 0
    },
    {
        "RShoulderPitch": 54.06825072166225,
        "RShoulderRoll": -36.883398785077866,
        "RElbowRoll": 43.1759989100897,
        "RElbowYaw": 0,
        "LShoulderPitch": 71.76330258352183,
        "LShoulderRoll": 40.39244580103112,
        "LElbowRoll": 44.680399386807466,
        "LElbowYaw": 124.52779671899307
    },
    {
        "RShoulderPitch": 53.66858385255962,
        "RShoulderRoll": -36.612173946979254,
        "RElbowRoll": 43.147161106588726,
        "RElbowYaw": 0,
        "LShoulderPitch": 52.92521917400239,
        "LShoulderRoll": 37.245539852392334,
        "LElbowRoll": 37.30746446557515,
        "LElbowYaw": 0
    },
    {
        "RShoulderPitch": 52.5051363900338,
        "RShoulderRoll": -35.79088475381153,
        "RElbowRoll": 42.205477278865914,
        "RElbowYaw": 0,
        "LShoulderPitch": 52.43835735215172,
        "LShoulderRoll": 37.128000863350806,
        "LElbowRoll": 37.790133398591564,
        "LElbowYaw": 0
    },
    {
        "RShoulderPitch": 49.39395422814775,
        "RShoulderRoll": -36.31312958663944,
        "RElbowRoll": 43.55416534264748,
        "RElbowYaw": 0,
        "LShoulderPitch": 49.22506113225521,
        "LShoulderRoll": 37.1148891497754,
        "LElbowRoll": 43.02964834822566,
        "LElbowYaw": 110.24019800937828
    },
    {
        "RShoulderPitch": 49.39395422814775,
        "RShoulderRoll": -36.31312958663944,
        "RElbowRoll": 43.55416534264748,
        "RElbowYaw": 0,
        "LShoulderPitch": 49.22506113225521,
        "LShoulderRoll": 37.1148891497754,
        "LElbowRoll": 43.02964834822566,
        "LElbowYaw": 110.24019800937828
    },
    {
        "RShoulderPitch": 47.05474421570261,
        "RShoulderRoll": -36.36377102824865,
        "RElbowRoll": 44.48217230002774,
        "RElbowYaw": 0,
        "LShoulderPitch": 51.39007910666459,
        "LShoulderRoll": 39.75324121660653,
        "LElbowRoll": 41.69915045648253,
        "LElbowYaw": 119.45349552500402
    },
    {
        "RShoulderPitch": 48.236337070001866,
        "RShoulderRoll": -36.75903225727341,
        "RElbowRoll": 46.56258951281566,
        "RElbowYaw": 31.13611653793268,
        "LShoulderPitch": 50.07407895644921,
        "LShoulderRoll": 39.70887951166753,
        "LElbowRoll": 42.501755587578145,
        "LElbowYaw": 0
    },
    {
        "RShoulderPitch": 44.48695849754751,
        "RShoulderRoll": -35.65482187220851,
        "RElbowRoll": 44.31281704627912,
        "RElbowYaw": 35.9455209995315,
        "LShoulderPitch": 34.703637169207106,
        "LShoulderRoll": 33.55391184515208,
        "LElbowRoll": 34.08777977729187,
        "LElbowYaw": 0
    },
    {
        "RShoulderPitch": 40.34357164076485,
        "RShoulderRoll": -39.526570708631425,
        "RElbowRoll": 51.2327029996263,
        "RElbowYaw": 39.611048608200974,
        "LShoulderPitch": 41.9274034599884,
        "LShoulderRoll": 41.294998748732446,
        "LElbowRoll": 44.79791008704373,
        "LElbowYaw": -90
    },
    {
        "RShoulderPitch": 72.81595333775354,
        "RShoulderRoll": -46.25356214665772,
        "RElbowRoll": 86.83440365572783,
        "RElbowYaw": 90,
        "LShoulderPitch": 39.83249271300629,
        "LShoulderRoll": 40.54667511028841,
        "LElbowRoll": 50.274600116166795,
        "LElbowYaw": -90
    },
    {
        "RShoulderPitch": 72.6906212338445,
        "RShoulderRoll": -46.86497456271847,
        "RElbowRoll": 77.31490533754943,
        "RElbowYaw": 90,
        "LShoulderPitch": 24.701321042684185,
        "LShoulderRoll": 43.08810102373541,
        "LElbowRoll": 46.100733301870065,
        "LElbowYaw": -90
    },
    {
        "RShoulderPitch": 67.2106179586122,
        "RShoulderRoll": -48.01425510488466,
        "RElbowRoll": 79.1558931722219,
        "RElbowYaw": 90,
        "LShoulderPitch": 72.6518210365359,
        "LShoulderRoll": 48.39230071535263,
        "LElbowRoll": 77.45683572772785,
        "LElbowYaw": 167.32362557780843
    },
    {
        "RShoulderPitch": 51.93719417544701,
        "RShoulderRoll": -48.58890416100334,
        "RElbowRoll": 64.70448869378362,
        "RElbowYaw": 90,
        "LShoulderPitch": 36.712837472850815,
        "LShoulderRoll": 38.04576574320147,
        "LElbowRoll": 59.62269599230554,
        "LElbowYaw": -90
    },
    {
        "RShoulderPitch": 26.049172281689366,
        "RShoulderRoll": -30.522081157695176,
        "RElbowRoll": 52.8333075879527,
        "RElbowYaw": 0,
        "LShoulderPitch": 35.931747376207255,
        "LShoulderRoll": 38.864763050839315,
        "LElbowRoll": 57.93313296017196,
        "LElbowYaw": -90
    },
    {
        "RShoulderPitch": 24.35300562954221,
        "RShoulderRoll": -29.692666276665026,
        "RElbowRoll": 56.326245847848796,
        "RElbowYaw": 79.31301153941855,
        "LShoulderPitch": 25.373388518264306,
        "LShoulderRoll": 34.560705256157284,
        "LElbowRoll": 57.18345783208258,
        "LElbowYaw": 0
    },
    {
        "RShoulderPitch": 23.8081611395895,
        "RShoulderRoll": -29.9630995293229,
        "RElbowRoll": 55.492689738424986,
        "RElbowYaw": 0,
        "LShoulderPitch": 48.04321169235409,
        "LShoulderRoll": 55.07595189850583,
        "LElbowRoll": 72.3994329753747,
        "LElbowYaw": -90
    },
    {
        "RShoulderPitch": 22.720645554364438,
        "RShoulderRoll": -30.712095609478624,
        "RElbowRoll": 56.12915526129834,
        "RElbowYaw": 0,
        "LShoulderPitch": 49.13816864328608,
        "LShoulderRoll": 55.00008413104923,
        "LElbowRoll": 79.05466140668342,
        "LElbowYaw": -90
    },
    {
        "RShoulderPitch": 21.053984584168163,
        "RShoulderRoll": -31.596681605289213,
        "RElbowRoll": 64.04581347403742,
        "RElbowYaw": 96.95999713108516,
        "LShoulderPitch": 49.13343332685647,
        "LShoulderRoll": 55.10258657587166,
        "LElbowRoll": 79.60468278517673,
        "LElbowYaw": -90
    },
    {
        "RShoulderPitch": 19.87181480006062,
        "RShoulderRoll": -32.676249415879035,
        "RElbowRoll": 64.32895192806485,
        "RElbowYaw": 98.20966371866123,
        "LShoulderPitch": 45.68123626897562,
        "LShoulderRoll": 55.89960866795403,
        "LElbowRoll": 79.2547392700591,
        "LElbowYaw": -90
    },
    {
        "RShoulderPitch": 18.42234253487848,
        "RShoulderRoll": -33.66419513922747,
        "RElbowRoll": 65.58683400247057,
        "RElbowYaw": 101.7993867929404,
        "LShoulderPitch": 20.347973027968607,
        "LShoulderRoll": 41.69203895351486,
        "LElbowRoll": 61.32803728262208,
        "LElbowYaw": -90
    },
    {
        "RShoulderPitch": 16.37223247710611,
        "RShoulderRoll": -34.75442148405279,
        "RElbowRoll": 69.7184582681738,
        "RElbowYaw": 0,
        "LShoulderPitch": 11.386602981216328,
        "LShoulderRoll": 34.519396310305034,
        "LElbowRoll": 63.51805594508639,
        "LElbowYaw": 0
    },
    {
        "RShoulderPitch": 15.625595271699652,
        "RShoulderRoll": -35.42660784460611,
        "RElbowRoll": 70.1575696271599,
        "RElbowYaw": 0,
        "LShoulderPitch": 11.220791847401784,
        "LShoulderRoll": 35.370063472997224,
        "LElbowRoll": 66.15264271644219,
        "LElbowYaw": 0
    },
    {
        "RShoulderPitch": 14.070912898939383,
        "RShoulderRoll": -36.00997464789989,
        "RElbowRoll": 70.64826901973012,
        "RElbowYaw": 0,
        "LShoulderPitch": 10.761804839924437,
        "LShoulderRoll": 36.20484189902677,
        "LElbowRoll": 67.68450882526277,
        "LElbowYaw": 0
    },
    {
        "RShoulderPitch": 12.169918724336455,
        "RShoulderRoll": -36.373573133980756,
        "RElbowRoll": 71.63871505182419,
        "RElbowYaw": 0,
        "LShoulderPitch": 9.87531512963183,
        "LShoulderRoll": 36.8764872389405,
        "LElbowRoll": 69.22126446550757,
        "LElbowYaw": 0
    },
    {
        "RShoulderPitch": 12.169918724336455,
        "RShoulderRoll": -36.373573133980756,
        "RElbowRoll": 71.63871505182419,
        "RElbowYaw": 0,
        "LShoulderPitch": 9.87531512963183,
        "LShoulderRoll": 36.8764872389405,
        "LElbowRoll": 69.22126446550757,
        "LElbowYaw": 0
    },
    {
        "RShoulderPitch": 10.774303965568919,
        "RShoulderRoll": -37.17674132248084,
        "RElbowRoll": 74.62576750309523,
        "RElbowYaw": 0,
        "LShoulderPitch": 7.803376508716838,
        "LShoulderRoll": 38.07019500167492,
        "LElbowRoll": 73.04326276178013,
        "LElbowYaw": 0
    },
    {
        "RShoulderPitch": 9.629797556720845,
        "RShoulderRoll": -37.46790314428457,
        "RElbowRoll": 75.22782848866427,
        "RElbowYaw": 0,
        "LShoulderPitch": 6.819953885907694,
        "LShoulderRoll": 38.43667264510196,
        "LElbowRoll": 72.8876331531061,
        "LElbowYaw": 0
    },
    {
        "RShoulderPitch": 9.629797556720845,
        "RShoulderRoll": -37.46790314428457,
        "RElbowRoll": 75.22782848866427,
        "RElbowYaw": 0,
        "LShoulderPitch": 6.819953885907694,
        "LShoulderRoll": 38.43667264510196,
        "LElbowRoll": 72.8876331531061,
        "LElbowYaw": 0
    },
    {
        "RShoulderPitch": 8.043689927991238,
        "RShoulderRoll": -39.70254338810528,
        "RElbowRoll": 79.11950048698284,
        "RElbowYaw": 0,
        "LShoulderPitch": 4.546868448124869,
        "LShoulderRoll": 39.59857216251872,
        "LElbowRoll": 74.0183111603958,
        "LElbowYaw": 0
    },
    {
        "RShoulderPitch": 7.289911173255334,
        "RShoulderRoll": -40.82170640090716,
        "RElbowRoll": 79.77991090330495,
        "RElbowYaw": 0,
        "LShoulderPitch": 3.616713282273878,
        "LShoulderRoll": 40.01839991891139,
        "LElbowRoll": 74.7242216612316,
        "LElbowYaw": 0
    },
    {
        "RShoulderPitch": 6.776516887949185,
        "RShoulderRoll": -41.3240017118411,
        "RElbowRoll": 80.97233032408083,
        "RElbowYaw": 0,
        "LShoulderPitch": 2.9141572841239736,
        "LShoulderRoll": 40.10733077600067,
        "LElbowRoll": 75.61741781082321,
        "LElbowYaw": 0
    },
    {
        "RShoulderPitch": 6.183150018304389,
        "RShoulderRoll": -41.72996606344109,
        "RElbowRoll": 81.80036871044392,
        "RElbowYaw": 141.58148573454386,
        "LShoulderPitch": 1.97018312182945,
        "LShoulderRoll": 40.21853368991838,
        "LElbowRoll": 75.95165738237736,
        "LElbowYaw": 0
    },
    {
        "RShoulderPitch": 6.183150018304389,
        "RShoulderRoll": -41.72996606344109,
        "RElbowRoll": 81.80036871044392,
        "RElbowYaw": 141.58148573454386,
        "LShoulderPitch": 1.97018312182945,
        "LShoulderRoll": 40.21853368991838,
        "LElbowRoll": 75.95165738237736,
        "LElbowYaw": 0
    },
    {
        "RShoulderPitch": 5.629773126316223,
        "RShoulderRoll": -42.19130113494287,
        "RElbowRoll": 82.2290728441039,
        "RElbowYaw": 142.85510732882554,
        "LShoulderPitch": 1.2898446781805006,
        "LShoulderRoll": 40.558030857399594,
        "LElbowRoll": 76.4639228670766,
        "LElbowYaw": 0
    },
    {
        "RShoulderPitch": 5.2359755337218274,
        "RShoulderRoll": -42.45935523081822,
        "RElbowRoll": 82.8888073624956,
        "RElbowYaw": 144.50063861524512,
        "LShoulderPitch": 0.8043901134213627,
        "LShoulderRoll": 41.020209797719055,
        "LElbowRoll": 77.37179812429657,
        "LElbowYaw": 0
    },
    {
        "RShoulderPitch": 4.714350316230465,
        "RShoulderRoll": -43.164550106547836,
        "RElbowRoll": 83.90178183342654,
        "RElbowYaw": 146.3651559506713,
        "LShoulderPitch": 0.1344192848013961,
        "LShoulderRoll": 41.52928676020797,
        "LElbowRoll": 78.44902060033442,
        "LElbowYaw": 0
    },
    {
        "RShoulderPitch": 4.674382821498085,
        "RShoulderRoll": -43.387211658047875,
        "RElbowRoll": 84.3104367810151,
        "RElbowYaw": 146.85421151377076,
        "LShoulderPitch": 0.041651133630480786,
        "LShoulderRoll": 41.62158927221776,
        "LElbowRoll": 79.07297606742746,
        "LElbowYaw": 0
    },
    {
        "RShoulderPitch": 4.625792165301476,
        "RShoulderRoll": -43.48064266547125,
        "RElbowRoll": 84.66359481079142,
        "RElbowYaw": 147.40227835898256,
        "LShoulderPitch": -0.1878510282108724,
        "LShoulderRoll": 41.54896128997467,
        "LElbowRoll": 79.49929929608993,
        "LElbowYaw": 0
    },
    {
        "RShoulderPitch": 4.625792165301476,
        "RShoulderRoll": -43.48064266547125,
        "RElbowRoll": 84.66359481079142,
        "RElbowYaw": 147.40227835898256,
        "LShoulderPitch": -0.1878510282108724,
        "LShoulderRoll": 41.54896128997467,
        "LElbowRoll": 79.49929929608993,
        "LElbowYaw": 0
    },
    {
        "RShoulderPitch": 4.675768173829951,
        "RShoulderRoll": -43.60873955180909,
        "RElbowRoll": 85.36034064916807,
        "RElbowYaw": 148.1936700951921,
        "LShoulderPitch": -0.2653416592963002,
        "LShoulderRoll": 41.6183624796955,
        "LElbowRoll": 79.8235561493249,
        "LElbowYaw": 145.56912443270423
    },
    {
        "RShoulderPitch": 4.695852423995859,
        "RShoulderRoll": -43.6762583143363,
        "RElbowRoll": 85.68722616970028,
        "RElbowYaw": 148.63518777148974,
        "LShoulderPitch": 0.3103400142448294,
        "LShoulderRoll": 42.22962447469347,
        "LElbowRoll": 80.652550039584,
        "LElbowYaw": 146.5836525859781
    },
    {
        "RShoulderPitch": 4.704728333820725,
        "RShoulderRoll": -43.75740484914061,
        "RElbowRoll": 86.0537570152862,
        "RElbowYaw": 149.21091069273663,
        "LShoulderPitch": 0.24578305769364306,
        "LShoulderRoll": 42.16537785693656,
        "LElbowRoll": 81.13051080620767,
        "LElbowYaw": 147.55741236940753
    },
    {
        "RShoulderPitch": 4.823500439925624,
        "RShoulderRoll": -43.8341608901144,
        "RElbowRoll": 86.5052543324479,
        "RElbowYaw": 149.7769401685245,
        "LShoulderPitch": 0.4167435666608412,
        "LShoulderRoll": 42.28535287395612,
        "LElbowRoll": 81.61481953128634,
        "LElbowYaw": 148.60511425036745
    },
    {
        "RShoulderPitch": 5.458797702142121,
        "RShoulderRoll": -44.05372084206986,
        "RElbowRoll": 87.74072031127153,
        "RElbowYaw": 151.21456386653875,
        "LShoulderPitch": 1.4305917865732454,
        "LShoulderRoll": 43.07846918142645,
        "LElbowRoll": 83.3394042708027,
        "LElbowYaw": 151.97769253565917
    },
    {
        "RShoulderPitch": 5.7455558051021995,
        "RShoulderRoll": -44.129205400210104,
        "RElbowRoll": 88.04630881751979,
        "RElbowYaw": 90,
        "LShoulderPitch": 1.9064973349787095,
        "LShoulderRoll": 43.541787398354685,
        "LElbowRoll": 83.91296677964431,
        "LElbowYaw": 153.61379240387828
    },
    {
        "RShoulderPitch": 7.005642988668768,
        "RShoulderRoll": -43.949455986244416,
        "RElbowRoll": 88.6906345480851,
        "RElbowYaw": 90,
        "LShoulderPitch": 2.275298186602953,
        "LShoulderRoll": 43.72595480219369,
        "LElbowRoll": 84.30712743766424,
        "LElbowYaw": 155.23327175837034
    },
    {
        "RShoulderPitch": 7.417671089187749,
        "RShoulderRoll": -44.13989942097076,
        "RElbowRoll": 88.72106429813637,
        "RElbowYaw": 90,
        "LShoulderPitch": 3.284947534772371,
        "LShoulderRoll": 44.694347225068995,
        "LElbowRoll": 85.50901855974512,
        "LElbowYaw": 157.36453770914892
    },
    {
        "RShoulderPitch": 7.773736001982144,
        "RShoulderRoll": -44.30987996892945,
        "RElbowRoll": 88.35491717152047,
        "RElbowYaw": 90,
        "LShoulderPitch": 4.314870053621931,
        "LShoulderRoll": 45.574409204192094,
        "LElbowRoll": 86.14366464456727,
        "LElbowYaw": 159.0595251527156
    },
    {
        "RShoulderPitch": 8.09016370190676,
        "RShoulderRoll": -44.51121363910501,
        "RElbowRoll": 88.45087807006979,
        "RElbowYaw": 90,
        "LShoulderPitch": 4.766421368555257,
        "LShoulderRoll": 46.091704860417586,
        "LElbowRoll": 86.58886449719472,
        "LElbowYaw": 160.57498266604793
    },
    {
        "RShoulderPitch": 9.133406832248113,
        "RShoulderRoll": -44.610476503470075,
        "RElbowRoll": 87.77939967990099,
        "RElbowYaw": 90,
        "LShoulderPitch": 5.237198384003349,
        "LShoulderRoll": 46.861710960129834,
        "LElbowRoll": 86.69187974791988,
        "LElbowYaw": 161.70014777604467
    },
    {
        "RShoulderPitch": 9.133406832248113,
        "RShoulderRoll": -44.610476503470075,
        "RElbowRoll": 87.77939967990099,
        "RElbowYaw": 90,
        "LShoulderPitch": 5.237198384003349,
        "LShoulderRoll": 46.861710960129834,
        "LElbowRoll": 86.69187974791988,
        "LElbowYaw": 161.70014777604467
    },
    {
        "RShoulderPitch": 9.59125471657886,
        "RShoulderRoll": -44.97586490722591,
        "RElbowRoll": 87.1109331560596,
        "RElbowYaw": 90,
        "LShoulderPitch": 5.496811234495922,
        "LShoulderRoll": 47.67847155109391,
        "LElbowRoll": 86.5806927153601,
        "LElbowYaw": 162.29908762900726
    },
    {
        "RShoulderPitch": 10.080161244325808,
        "RShoulderRoll": -45.4454244152191,
        "RElbowRoll": 86.52673020475417,
        "RElbowYaw": 90,
        "LShoulderPitch": 5.922681869575882,
        "LShoulderRoll": 48.663509177120964,
        "LElbowRoll": 87.09753716776507,
        "LElbowYaw": -90
    },
    {
        "RShoulderPitch": 10.510269971184442,
        "RShoulderRoll": -45.69859893947256,
        "RElbowRoll": 86.13776138972985,
        "RElbowYaw": 90,
        "LShoulderPitch": 6.372767280489626,
        "LShoulderRoll": 49.599372780163634,
        "LElbowRoll": 87.44553996205217,
        "LElbowYaw": -90
    },
    {
        "RShoulderPitch": 11.11284040083936,
        "RShoulderRoll": -46.90095222992932,
        "RElbowRoll": 84.95265569954925,
        "RElbowYaw": 90,
        "LShoulderPitch": -3.8111706342217464,
        "LShoulderRoll": 48.994024925768585,
        "LElbowRoll": 73.93821419971609,
        "LElbowYaw": -90
    },
    {
        "RShoulderPitch": 11.11284040083936,
        "RShoulderRoll": -46.90095222992932,
        "RElbowRoll": 84.95265569954925,
        "RElbowYaw": 90,
        "LShoulderPitch": -3.8111706342217464,
        "LShoulderRoll": 48.994024925768585,
        "LElbowRoll": 73.93821419971609,
        "LElbowYaw": -90
    },
    {
        "RShoulderPitch": 11.401843765165793,
        "RShoulderRoll": -47.321346554644244,
        "RElbowRoll": 84.40909986732838,
        "RElbowYaw": 90,
        "LShoulderPitch": 7.094179055000765,
        "LShoulderRoll": 53.6209371832733,
        "LElbowRoll": 86.23261954755085,
        "LElbowYaw": -90
    },
    {
        "RShoulderPitch": 11.660310959895,
        "RShoulderRoll": -47.51097706919589,
        "RElbowRoll": 83.6448115035884,
        "RElbowYaw": 90,
        "LShoulderPitch": 8.42139911695429,
        "LShoulderRoll": 54.345173388689616,
        "LElbowRoll": 86.19477716261588,
        "LElbowYaw": -90
    },
    {
        "RShoulderPitch": 12.10128124244197,
        "RShoulderRoll": -47.931832607249184,
        "RElbowRoll": 83.34614855014634,
        "RElbowYaw": 90,
        "LShoulderPitch": 8.533946468106308,
        "LShoulderRoll": 54.30485307662622,
        "LElbowRoll": 85.70195811080951,
        "LElbowYaw": -90
    },
    {
        "RShoulderPitch": 12.709566225868826,
        "RShoulderRoll": -48.79797066636182,
        "RElbowRoll": 83.0598574360869,
        "RElbowYaw": 90,
        "LShoulderPitch": 9.603424553781693,
        "LShoulderRoll": 55.30294517004403,
        "LElbowRoll": 85.70305152807971,
        "LElbowYaw": -90
    },
    {
        "RShoulderPitch": 13.095954144083393,
        "RShoulderRoll": -49.4591036167416,
        "RElbowRoll": 82.59430407783309,
        "RElbowYaw": 90,
        "LShoulderPitch": 9.89813452201605,
        "LShoulderRoll": 55.30149424103431,
        "LElbowRoll": 85.48834622169569,
        "LElbowYaw": -90
    },
    {
        "RShoulderPitch": 13.309183162342535,
        "RShoulderRoll": -49.767261806983846,
        "RElbowRoll": 82.3125984073886,
        "RElbowYaw": 90,
        "LShoulderPitch": 10.35069299147149,
        "LShoulderRoll": 55.5203002395543,
        "LElbowRoll": 85.28439569851754,
        "LElbowYaw": -90
    },
    {
        "RShoulderPitch": 13.593482695422807,
        "RShoulderRoll": -50.116361939863616,
        "RElbowRoll": 82.44779804350023,
        "RElbowYaw": 90,
        "LShoulderPitch": 10.86146017706021,
        "LShoulderRoll": 55.79989244290773,
        "LElbowRoll": 85.23078784447345,
        "LElbowYaw": -90
    },
    {
        "RShoulderPitch": 13.85364700569481,
        "RShoulderRoll": -50.333579317483505,
        "RElbowRoll": 82.53647420613962,
        "RElbowYaw": 90,
        "LShoulderPitch": 11.052938223440009,
        "LShoulderRoll": 56.006705587224616,
        "LElbowRoll": 85.21123322053096,
        "LElbowYaw": -90
    },
    {
        "RShoulderPitch": 13.87789395333381,
        "RShoulderRoll": -50.41498787716016,
        "RElbowRoll": 82.54385862721497,
        "RElbowYaw": 90,
        "LShoulderPitch": 11.520583871300715,
        "LShoulderRoll": 56.183013081615634,
        "LElbowRoll": 85.40188226015344,
        "LElbowYaw": -90
    },
    {
        "RShoulderPitch": 13.968867968905627,
        "RShoulderRoll": -50.429758680547664,
        "RElbowRoll": 82.70561042454892,
        "RElbowYaw": 90,
        "LShoulderPitch": 11.782113667499502,
        "LShoulderRoll": 56.15304196293457,
        "LElbowRoll": 85.46370899466903,
        "LElbowYaw": -90
    },
    {
        "RShoulderPitch": 14.039617725643666,
        "RShoulderRoll": -50.41271549145857,
        "RElbowRoll": 82.63493535395074,
        "RElbowYaw": 90,
        "LShoulderPitch": 12.147839570620505,
        "LShoulderRoll": 56.10144913523005,
        "LElbowRoll": 85.60855304798662,
        "LElbowYaw": -90
    },
    {
        "RShoulderPitch": 13.746430989175678,
        "RShoulderRoll": -49.92685340581065,
        "RElbowRoll": 82.70840396230493,
        "RElbowYaw": 90,
        "LShoulderPitch": 12.513817536156651,
        "LShoulderRoll": 55.90920932686773,
        "LElbowRoll": 85.72286427551009,
        "LElbowYaw": -90
    },
    {
        "RShoulderPitch": 13.901464423882032,
        "RShoulderRoll": -49.56797628745719,
        "RElbowRoll": 82.82301576594838,
        "RElbowYaw": 90,
        "LShoulderPitch": 13.08639713766108,
        "LShoulderRoll": 55.780112086284134,
        "LElbowRoll": 85.482962029939,
        "LElbowYaw": -90
    },
    {
        "RShoulderPitch": 14.055841298905392,
        "RShoulderRoll": -49.291468281655604,
        "RElbowRoll": 82.92848338118233,
        "RElbowYaw": 90,
        "LShoulderPitch": 13.337119025100094,
        "LShoulderRoll": 55.5962143437796,
        "LElbowRoll": 85.62591577235763,
        "LElbowYaw": -90
    },
    {
        "RShoulderPitch": 14.268275326591308,
        "RShoulderRoll": -48.65606543717288,
        "RElbowRoll": 83.11987882402934,
        "RElbowYaw": 90,
        "LShoulderPitch": 13.433329117966451,
        "LShoulderRoll": 55.04582827114744,
        "LElbowRoll": 85.63513788237049,
        "LElbowYaw": -90
    },
    {
        "RShoulderPitch": 14.410048572691622,
        "RShoulderRoll": -48.224401567629656,
        "RElbowRoll": 83.33608515536372,
        "RElbowYaw": 90,
        "LShoulderPitch": 13.782942460033055,
        "LShoulderRoll": 54.49782082004052,
        "LElbowRoll": 85.73683590197574,
        "LElbowYaw": -90
    },
    {
        "RShoulderPitch": 14.631501683959002,
        "RShoulderRoll": -47.75972388215364,
        "RElbowRoll": 83.52057181465679,
        "RElbowYaw": 90,
        "LShoulderPitch": 13.963564972415924,
        "LShoulderRoll": 54.173753586316586,
        "LElbowRoll": 85.82063948666512,
        "LElbowYaw": -90
    },
    {
        "RShoulderPitch": 14.870230615740013,
        "RShoulderRoll": -47.355407088443215,
        "RElbowRoll": 83.77093018043843,
        "RElbowYaw": 90,
        "LShoulderPitch": 14.15944106602231,
        "LShoulderRoll": 53.92620711976145,
        "LElbowRoll": 85.84508936367709,
        "LElbowYaw": -90
    },
    {
        "RShoulderPitch": 15.123885171520442,
        "RShoulderRoll": -47.21493790535383,
        "RElbowRoll": 83.8615196707314,
        "RElbowYaw": 90,
        "LShoulderPitch": 14.395217613471402,
        "LShoulderRoll": 53.715133961690974,
        "LElbowRoll": 85.79687923127895,
        "LElbowYaw": -90
    },
    {
        "RShoulderPitch": 15.335154908125176,
        "RShoulderRoll": -47.109365602401965,
        "RElbowRoll": 83.91593827710899,
        "RElbowYaw": 90,
        "LShoulderPitch": 14.434435772550614,
        "LShoulderRoll": 53.49829251474632,
        "LElbowRoll": 85.79444110490158,
        "LElbowYaw": -90
    },
    {
        "RShoulderPitch": 15.214243910544752,
        "RShoulderRoll": -46.11863129316284,
        "RElbowRoll": 84.12477619880522,
        "RElbowYaw": 90,
        "LShoulderPitch": 14.490878250216653,
        "LShoulderRoll": 53.39063945314672,
        "LElbowRoll": 85.78971019062442,
        "LElbowYaw": -90
    },
    {
        "RShoulderPitch": 15.348877917135425,
        "RShoulderRoll": -46.104965054864834,
        "RElbowRoll": 85.00750471063104,
        "RElbowYaw": 90,
        "LShoulderPitch": 14.559756396713752,
        "LShoulderRoll": 53.400031733335915,
        "LElbowRoll": 85.82358064665088,
        "LElbowYaw": -90
    },
    {
        "RShoulderPitch": 15.29298413760084,
        "RShoulderRoll": -45.80154726351202,
        "RElbowRoll": 85.21086210334114,
        "RElbowYaw": 90,
        "LShoulderPitch": 14.604481885897826,
        "LShoulderRoll": 53.30623492938367,
        "LElbowRoll": 85.86607416009896,
        "LElbowYaw": -90
    },
    {
        "RShoulderPitch": 15.400291853735027,
        "RShoulderRoll": -45.81975111487848,
        "RElbowRoll": 84.92841878320148,
        "RElbowYaw": 90,
        "LShoulderPitch": 14.580191882428366,
        "LShoulderRoll": 53.00791227656831,
        "LElbowRoll": 85.91957613245333,
        "LElbowYaw": -90
    },
    {
        "RShoulderPitch": 15.474648496266497,
        "RShoulderRoll": -45.77602235329607,
        "RElbowRoll": 84.90833451971454,
        "RElbowYaw": 90,
        "LShoulderPitch": 14.580088155576547,
        "LShoulderRoll": 53.07464532444319,
        "LElbowRoll": 85.91725835653371,
        "LElbowYaw": -90
    },
    {
        "RShoulderPitch": 15.559369259354384,
        "RShoulderRoll": -45.75384723111703,
        "RElbowRoll": 84.44660417926724,
        "RElbowYaw": 90,
        "LShoulderPitch": 15.042935849993498,
        "LShoulderRoll": 53.23669364746888,
        "LElbowRoll": 86.25631283795555,
        "LElbowYaw": -90
    },
    {
        "RShoulderPitch": 15.828348338919,
        "RShoulderRoll": -45.76353899191885,
        "RElbowRoll": 84.4298649930128,
        "RElbowYaw": 90,
        "LShoulderPitch": 15.075195071646704,
        "LShoulderRoll": 53.20222781578749,
        "LElbowRoll": 86.44148763651964,
        "LElbowYaw": -90
    },
    {
        "RShoulderPitch": 15.899697632573023,
        "RShoulderRoll": -45.75445732813598,
        "RElbowRoll": 84.23945431725618,
        "RElbowYaw": 90,
        "LShoulderPitch": 15.12499943876928,
        "LShoulderRoll": 53.18365048706049,
        "LElbowRoll": 86.34606868769451,
        "LElbowYaw": -90
    },
    {
        "RShoulderPitch": 16.211283589897164,
        "RShoulderRoll": -45.638192699008876,
        "RElbowRoll": 83.99022068497949,
        "RElbowYaw": 90,
        "LShoulderPitch": 15.269839885718639,
        "LShoulderRoll": 53.11723149782335,
        "LElbowRoll": 86.23902806697265,
        "LElbowYaw": -90
    },
    {
        "RShoulderPitch": 16.449169299768812,
        "RShoulderRoll": -45.53850470289403,
        "RElbowRoll": 83.42727842796035,
        "RElbowYaw": 90,
        "LShoulderPitch": 15.48261332823472,
        "LShoulderRoll": 53.078112648419975,
        "LElbowRoll": 86.05313677689338,
        "LElbowYaw": 172.8745674982515
    },
    {
        "RShoulderPitch": 17.039076157282068,
        "RShoulderRoll": -45.60471493715427,
        "RElbowRoll": 83.27525097376717,
        "RElbowYaw": 90,
        "LShoulderPitch": 15.647531019732341,
        "LShoulderRoll": 52.99843733218872,
        "LElbowRoll": 85.98064853045844,
        "LElbowYaw": 172.32961011900807
    },
    {
        "RShoulderPitch": 17.71503470191749,
        "RShoulderRoll": -45.29047904666832,
        "RElbowRoll": 83.58583379489923,
        "RElbowYaw": 90,
        "LShoulderPitch": 16.461233115701432,
        "LShoulderRoll": 53.28598094469852,
        "LElbowRoll": 86.02782473395648,
        "LElbowYaw": 172.00425186634214
    },
    {
        "RShoulderPitch": 17.71503470191749,
        "RShoulderRoll": -45.29047904666832,
        "RElbowRoll": 83.58583379489923,
        "RElbowYaw": 90,
        "LShoulderPitch": 16.461233115701432,
        "LShoulderRoll": 53.28598094469852,
        "LElbowRoll": 86.02782473395648,
        "LElbowYaw": 172.00425186634214
    },
    {
        "RShoulderPitch": 17.936239482432157,
        "RShoulderRoll": -45.055097022265606,
        "RElbowRoll": 83.3035199133556,
        "RElbowYaw": 90,
        "LShoulderPitch": 16.712600071254087,
        "LShoulderRoll": 53.21453608452085,
        "LElbowRoll": 85.86049143186013,
        "LElbowYaw": 171.20679691308123
    },
    {
        "RShoulderPitch": 18.745810129408284,
        "RShoulderRoll": -44.660616999106615,
        "RElbowRoll": 82.66642135459114,
        "RElbowYaw": 90,
        "LShoulderPitch": 18.335460202194355,
        "LShoulderRoll": 52.87384909525503,
        "LElbowRoll": 86.89469703669917,
        "LElbowYaw": 169.65901495198844
    },
    {
        "RShoulderPitch": 19.118437439338322,
        "RShoulderRoll": -44.50894471797831,
        "RElbowRoll": 82.8168679424156,
        "RElbowYaw": 90,
        "LShoulderPitch": 18.85844831445307,
        "LShoulderRoll": 52.94436498363627,
        "LElbowRoll": 87.06798570851132,
        "LElbowYaw": 169.00146246073592
    },
    {
        "RShoulderPitch": 19.227248924492088,
        "RShoulderRoll": -44.28450758123596,
        "RElbowRoll": 82.70332418575993,
        "RElbowYaw": 133.58479047072518,
        "LShoulderPitch": 19.23729964778454,
        "LShoulderRoll": 52.89069906513415,
        "LElbowRoll": 87.47020087036903,
        "LElbowYaw": 168.29941740928686
    },
    {
        "RShoulderPitch": 19.227248924492088,
        "RShoulderRoll": -44.28450758123596,
        "RElbowRoll": 82.70332418575993,
        "RElbowYaw": 133.58479047072518,
        "LShoulderPitch": 19.23729964778454,
        "LShoulderRoll": 52.89069906513415,
        "LElbowRoll": 87.47020087036903,
        "LElbowYaw": 168.29941740928686
    },
    {
        "RShoulderPitch": 19.335007788326678,
        "RShoulderRoll": -44.08427128307492,
        "RElbowRoll": 81.82631823839428,
        "RElbowYaw": 131.5797625623,
        "LShoulderPitch": 19.719027759991604,
        "LShoulderRoll": 52.716682519237935,
        "LElbowRoll": 87.5771997896982,
        "LElbowYaw": 167.2220199814016
    },
    {
        "RShoulderPitch": 19.205913234707523,
        "RShoulderRoll": -43.945600379905585,
        "RElbowRoll": 80.9228634197477,
        "RElbowYaw": 129.92417649605852,
        "LShoulderPitch": 20.109025184012054,
        "LShoulderRoll": 52.611940320459254,
        "LElbowRoll": 87.6790119458272,
        "LElbowYaw": 0
    },
    {
        "RShoulderPitch": 18.846852952436848,
        "RShoulderRoll": -43.68495070421374,
        "RElbowRoll": 79.82294845972855,
        "RElbowYaw": 128.1294388873385,
        "LShoulderPitch": 20.954737854773157,
        "LShoulderRoll": 52.568231115391725,
        "LElbowRoll": 87.92347270583676,
        "LElbowYaw": 0
    },
    {
        "RShoulderPitch": 18.591264409306504,
        "RShoulderRoll": -43.41974218527078,
        "RElbowRoll": 78.9696419002659,
        "RElbowYaw": 0,
        "LShoulderPitch": 21.922548668507815,
        "LShoulderRoll": 52.475736688017946,
        "LElbowRoll": 88.20506288852872,
        "LElbowYaw": 0
    },
    {
        "RShoulderPitch": 18.46850787451659,
        "RShoulderRoll": -42.68901188587699,
        "RElbowRoll": 77.42288588010108,
        "RElbowYaw": 0,
        "LShoulderPitch": 22.943504182997813,
        "LShoulderRoll": 51.495075768646764,
        "LElbowRoll": 85.84868450858946,
        "LElbowYaw": 0
    },
    {
        "RShoulderPitch": 18.179487681366155,
        "RShoulderRoll": -42.3564008632902,
        "RElbowRoll": 76.1715861818493,
        "RElbowYaw": 0,
        "LShoulderPitch": 22.294572374493868,
        "LShoulderRoll": 49.540238299591984,
        "LElbowRoll": 83.23051259816619,
        "LElbowYaw": 0
    },
    {
        "RShoulderPitch": 18.179487681366155,
        "RShoulderRoll": -42.3564008632902,
        "RElbowRoll": 76.1715861818493,
        "RElbowYaw": 0,
        "LShoulderPitch": 22.294572374493868,
        "LShoulderRoll": 49.540238299591984,
        "LElbowRoll": 83.23051259816619,
        "LElbowYaw": 0
    },
    {
        "RShoulderPitch": 17.844283596170357,
        "RShoulderRoll": -41.67223200306302,
        "RElbowRoll": 75.43286454258606,
        "RElbowYaw": 0,
        "LShoulderPitch": 22.19092142196594,
        "LShoulderRoll": 48.616374495838464,
        "LElbowRoll": 81.16120190287701,
        "LElbowYaw": 0
    },
    {
        "RShoulderPitch": 17.74126752462007,
        "RShoulderRoll": -41.141497126469275,
        "RElbowRoll": 74.27352970030637,
        "RElbowYaw": 0,
        "LShoulderPitch": 22.49281645778011,
        "LShoulderRoll": 47.65389462294771,
        "LElbowRoll": 79.5336959145935,
        "LElbowYaw": 0
    },
    {
        "RShoulderPitch": 17.464390527223173,
        "RShoulderRoll": -40.270335489345506,
        "RElbowRoll": 73.5069455208813,
        "RElbowYaw": 0,
        "LShoulderPitch": 23.91494630230524,
        "LShoulderRoll": 46.98134182020649,
        "LElbowRoll": 77.88972588370164,
        "LElbowYaw": 0
    },
    {
        "RShoulderPitch": 17.93218366189039,
        "RShoulderRoll": -39.24848152709731,
        "RElbowRoll": 72.41459272444447,
        "RElbowYaw": 0,
        "LShoulderPitch": 25.42847779340468,
        "LShoulderRoll": 46.47586546010998,
        "LElbowRoll": 75.3442095665065,
        "LElbowYaw": 0
    },
    {
        "RShoulderPitch": 18.605250138365463,
        "RShoulderRoll": -38.412233809731866,
        "RElbowRoll": 71.68357788668222,
        "RElbowYaw": 0,
        "LShoulderPitch": 25.864307342869722,
        "LShoulderRoll": 44.097453446241325,
        "LElbowRoll": 74.48339799266898,
        "LElbowYaw": 0
    },
    {
        "RShoulderPitch": 20.32496513895174,
        "RShoulderRoll": -37.81101242019509,
        "RElbowRoll": 69.03748314031353,
        "RElbowYaw": 0,
        "LShoulderPitch": 27.866353712636624,
        "LShoulderRoll": 43.89049774905833,
        "LElbowRoll": 72.95725812482594,
        "LElbowYaw": 0
    },
    {
        "RShoulderPitch": 20.906739608136874,
        "RShoulderRoll": -36.624072407234586,
        "RElbowRoll": 67.58454935743747,
        "RElbowYaw": 0,
        "LShoulderPitch": 25.96562302229134,
        "LShoulderRoll": 37.71040628917176,
        "LElbowRoll": 67.80109698860485,
        "LElbowYaw": 0
    },
    {
        "RShoulderPitch": 36.05172949798149,
        "RShoulderRoll": -43.1905481936619,
        "RElbowRoll": 66.70524094354715,
        "RElbowYaw": 71.17065790110473,
        "LShoulderPitch": 28.143947099070424,
        "LShoulderRoll": 39.5005307625114,
        "LElbowRoll": 68.08258360264425,
        "LElbowYaw": 0
    },
    {
        "RShoulderPitch": 25.41004155029671,
        "RShoulderRoll": -32.927892280852944,
        "RElbowRoll": 65.15930720851607,
        "RElbowYaw": 0,
        "LShoulderPitch": 27.91583164415446,
        "LShoulderRoll": 39.75456690622724,
        "LElbowRoll": 68.773298888649,
        "LElbowYaw": -90
    },
    {
        "RShoulderPitch": 49.847742352959,
        "RShoulderRoll": -47.70520285036045,
        "RElbowRoll": 74.33948245580264,
        "RElbowYaw": 54.58089475220622,
        "LShoulderPitch": 29.242452525632643,
        "LShoulderRoll": 39.404598912203866,
        "LElbowRoll": 67.60905378873352,
        "LElbowYaw": -90
    },
    {
        "RShoulderPitch": 52.81009829846012,
        "RShoulderRoll": -49.444995277428546,
        "RElbowRoll": 71.35605708003042,
        "RElbowYaw": 90,
        "LShoulderPitch": 26.932242586116715,
        "LShoulderRoll": 33.57764396776253,
        "LElbowRoll": 47.77693787837319,
        "LElbowYaw": -90
    },
    {
        "RShoulderPitch": 58.92246401547234,
        "RShoulderRoll": -48.83018732672826,
        "RElbowRoll": 74.27284664957656,
        "RElbowYaw": 90,
        "LShoulderPitch": 27.690844618037545,
        "LShoulderRoll": 33.54615603180693,
        "LElbowRoll": 53.40588202623381,
        "LElbowYaw": 0
    },
    {
        "RShoulderPitch": 82.3061455495975,
        "RShoulderRoll": -44.74633752157944,
        "RElbowRoll": 90.93878949874235,
        "RElbowYaw": 90,
        "LShoulderPitch": 35.81392589881789,
        "LShoulderRoll": 41.114921649578804,
        "LElbowRoll": 64.17493953715652,
        "LElbowYaw": -90
    },
    {
        "RShoulderPitch": 83.06300090276952,
        "RShoulderRoll": -43.30315868398997,
        "RElbowRoll": 90.68364611954357,
        "RElbowYaw": 90,
        "LShoulderPitch": 37.99687463043401,
        "LShoulderRoll": 43.00761447834917,
        "LElbowRoll": 51.635475966422774,
        "LElbowYaw": 0
    },
    {
        "RShoulderPitch": 34.07632769032549,
        "RShoulderRoll": -42.04615942884153,
        "RElbowRoll": 49.5603117056709,
        "RElbowYaw": 39.17576481640713,
        "LShoulderPitch": 40.920205121998706,
        "LShoulderRoll": 45.593047941022384,
        "LElbowRoll": 52.743591911679744,
        "LElbowYaw": -90
    },
    {
        "RShoulderPitch": 34.9382843401373,
        "RShoulderRoll": -41.91564257397754,
        "RElbowRoll": 45.152388709323304,
        "RElbowYaw": 0,
        "LShoulderPitch": 44.689464747195366,
        "LShoulderRoll": 48.26909676330599,
        "LElbowRoll": 52.106014292480026,
        "LElbowYaw": -90
    },
    {
        "RShoulderPitch": 30.183174313233557,
        "RShoulderRoll": -30.600630955783743,
        "RElbowRoll": 52.15050128757085,
        "RElbowYaw": 38.66188504214406,
        "LShoulderPitch": 34.74366863795217,
        "LShoulderRoll": 38.80823033049641,
        "LElbowRoll": 61.95282464857351,
        "LElbowYaw": 98.07200388711036
    },
    {
        "RShoulderPitch": 37.458336688050636,
        "RShoulderRoll": -29.307222103940614,
        "RElbowRoll": 43.91993898419497,
        "RElbowYaw": 31.975960882919665,
        "LShoulderPitch": 52.162293209782185,
        "LShoulderRoll": 52.0846049298639,
        "LElbowRoll": 51.22298509147157,
        "LElbowYaw": 0
    },
    {
        "RShoulderPitch": 37.99558229607358,
        "RShoulderRoll": -30.95530360769109,
        "RElbowRoll": 45.930883643368645,
        "RElbowYaw": 26.08021874059591,
        "LShoulderPitch": 39.49577779426844,
        "LShoulderRoll": 39.93079199153928,
        "LElbowRoll": 49.09857494716735,
        "LElbowYaw": 0
    },
    {
        "RShoulderPitch": 38.80313475846124,
        "RShoulderRoll": -30.92959755370263,
        "RElbowRoll": 46.73816811861266,
        "RElbowYaw": 21.931005714640506,
        "LShoulderPitch": 39.6426244095984,
        "LShoulderRoll": 39.273145711188484,
        "LElbowRoll": 49.570282711029876,
        "LElbowYaw": 0
    },
    {
        "RShoulderPitch": 39.96176353134669,
        "RShoulderRoll": -32.21594215390787,
        "RElbowRoll": 53.07358569534051,
        "RElbowYaw": 21.258156113276094,
        "LShoulderPitch": 40.93009509636043,
        "LShoulderRoll": 39.23134218288608,
        "LElbowRoll": 58.41229563642047,
        "LElbowYaw": 0
    },
    {
        "RShoulderPitch": 40.19782614575389,
        "RShoulderRoll": -32.96136649911698,
        "RElbowRoll": 54.96675589417406,
        "RElbowYaw": 0,
        "LShoulderPitch": 41.537261392349066,
        "LShoulderRoll": 39.25178545314524,
        "LElbowRoll": 51.96088490670965,
        "LElbowYaw": 0
    },
    {
        "RShoulderPitch": 42.18218191633306,
        "RShoulderRoll": -33.08230026299716,
        "RElbowRoll": 48.93850879273515,
        "RElbowYaw": 0,
        "LShoulderPitch": 42.64362894152555,
        "LShoulderRoll": 39.60805907409484,
        "LElbowRoll": 51.75758681499809,
        "LElbowYaw": 0
    },
    {
        "RShoulderPitch": 45.03045370465399,
        "RShoulderRoll": -34.27891270444998,
        "RElbowRoll": 48.83299480482276,
        "RElbowYaw": 0,
        "LShoulderPitch": 43.929272979158505,
        "LShoulderRoll": 39.45519227505484,
        "LElbowRoll": 51.927899987535255,
        "LElbowYaw": 0
    },
    {
        "RShoulderPitch": 46.208713018395926,
        "RShoulderRoll": -34.406226871411064,
        "RElbowRoll": 50.25501095290343,
        "RElbowYaw": 0,
        "LShoulderPitch": 45.60367576910399,
        "LShoulderRoll": 39.79056070246281,
        "LElbowRoll": 50.98526313448389,
        "LElbowYaw": 0
    },
    {
        "RShoulderPitch": 48.726980627664474,
        "RShoulderRoll": -35.660303360655426,
        "RElbowRoll": 50.31382369552588,
        "RElbowYaw": 0,
        "LShoulderPitch": 46.75433778408653,
        "LShoulderRoll": 40.2846456031573,
        "LElbowRoll": 50.966049907163665,
        "LElbowYaw": 0
    },
    {
        "RShoulderPitch": 49.292268155465806,
        "RShoulderRoll": -35.95521581306306,
        "RElbowRoll": 50.560735333964146,
        "RElbowYaw": 0,
        "LShoulderPitch": 50.367720692821905,
        "LShoulderRoll": 43.93142678392091,
        "LElbowRoll": 53.04173717543922,
        "LElbowYaw": 0
    },
    {
        "RShoulderPitch": 50.75546956489878,
        "RShoulderRoll": -35.30980511213884,
        "RElbowRoll": 49.84828367424717,
        "RElbowYaw": 0,
        "LShoulderPitch": 50.457584213543306,
        "LShoulderRoll": 42.26364234134056,
        "LElbowRoll": 51.53550687639648,
        "LElbowYaw": 0
    },
    {
        "RShoulderPitch": 51.79945711011016,
        "RShoulderRoll": -35.776184677224975,
        "RElbowRoll": 49.723497310275974,
        "RElbowYaw": 0,
        "LShoulderPitch": 52.90255054203272,
        "LShoulderRoll": 43.00191814078344,
        "LElbowRoll": 51.14063485091043,
        "LElbowYaw": 0
    },
    {
        "RShoulderPitch": 52.87853739767849,
        "RShoulderRoll": -35.87255208432976,
        "RElbowRoll": 50.19526027192177,
        "RElbowYaw": 0,
        "LShoulderPitch": 53.85333785597749,
        "LShoulderRoll": 43.09236130955224,
        "LElbowRoll": 50.50912118451714,
        "LElbowYaw": 0
    },
    {
        "RShoulderPitch": 52.87853739767849,
        "RShoulderRoll": -35.87255208432976,
        "RElbowRoll": 50.19526027192177,
        "RElbowYaw": 0,
        "LShoulderPitch": 53.85333785597749,
        "LShoulderRoll": 43.09236130955224,
        "LElbowRoll": 50.50912118451714,
        "LElbowYaw": 0
    },
    {
        "RShoulderPitch": 55.755726881351,
        "RShoulderRoll": -37.37245324218752,
        "RElbowRoll": 51.126989793959524,
        "RElbowYaw": 0,
        "LShoulderPitch": 55.51584369798823,
        "LShoulderRoll": 43.8766776523141,
        "LElbowRoll": 50.53694377822143,
        "LElbowYaw": 0
    },
    {
        "RShoulderPitch": 56.553676292176235,
        "RShoulderRoll": -36.89947581027521,
        "RElbowRoll": 50.69308284854526,
        "RElbowYaw": 0,
        "LShoulderPitch": 56.25790929904584,
        "LShoulderRoll": 44.19651646345727,
        "LElbowRoll": 50.14939992462834,
        "LElbowYaw": 0
    },
    {
        "RShoulderPitch": 58.62167333012627,
        "RShoulderRoll": -35.99502589287839,
        "RElbowRoll": 48.87252151879295,
        "RElbowYaw": 0,
        "LShoulderPitch": 58.88453176816909,
        "LShoulderRoll": 46.482656601724514,
        "LElbowRoll": 50.375412372925325,
        "LElbowYaw": 0
    },
    {
        "RShoulderPitch": 59.20914231486319,
        "RShoulderRoll": -36.25478060568801,
        "RElbowRoll": 48.11297296887949,
        "RElbowYaw": 0,
        "LShoulderPitch": 68.67078738116669,
        "LShoulderRoll": 46.214062030002715,
        "LElbowRoll": 49.68538083684277,
        "LElbowYaw": 0
    },
    {
        "RShoulderPitch": 59.20914231486319,
        "RShoulderRoll": -36.25478060568801,
        "RElbowRoll": 48.11297296887949,
        "RElbowYaw": 0,
        "LShoulderPitch": 68.67078738116669,
        "LShoulderRoll": 46.214062030002715,
        "LElbowRoll": 49.68538083684277,
        "LElbowYaw": 0
    },
    {
        "RShoulderPitch": 71.49186370419122,
        "RShoulderRoll": -31.953467192139442,
        "RElbowRoll": 44.189768018306495,
        "RElbowYaw": 0,
        "LShoulderPitch": 68.88866958883263,
        "LShoulderRoll": 45.70710883501194,
        "LElbowRoll": 48.066506028140964,
        "LElbowYaw": 0
    },
    {
        "RShoulderPitch": 71.37511497149612,
        "RShoulderRoll": -31.905224908695065,
        "RElbowRoll": 43.11524456499981,
        "RElbowYaw": 0,
        "LShoulderPitch": 68.99443464667812,
        "LShoulderRoll": 45.58523705464084,
        "LElbowRoll": 47.43994090668312,
        "LElbowYaw": 0
    },
    {
        "RShoulderPitch": 71.45633013828557,
        "RShoulderRoll": -31.93062904068755,
        "RElbowRoll": 42.17538439963741,
        "RElbowYaw": 0,
        "LShoulderPitch": 69.4488515334651,
        "LShoulderRoll": 45.47539380235798,
        "LElbowRoll": 46.95545296510625,
        "LElbowYaw": 0
    },
    {
        "RShoulderPitch": 71.71154446576651,
        "RShoulderRoll": -31.89464731082936,
        "RElbowRoll": 41.44529138321923,
        "RElbowYaw": 0,
        "LShoulderPitch": 70.04859109772309,
        "LShoulderRoll": 45.48386538510913,
        "LElbowRoll": 46.69006801511733,
        "LElbowYaw": 0
    },
    {
        "RShoulderPitch": 71.71154446576651,
        "RShoulderRoll": -31.89464731082936,
        "RElbowRoll": 41.44529138321923,
        "RElbowYaw": 0,
        "LShoulderPitch": 70.04859109772309,
        "LShoulderRoll": 45.48386538510913,
        "LElbowRoll": 46.69006801511733,
        "LElbowYaw": 0
    },
    {
        "RShoulderPitch": 72.12346622584948,
        "RShoulderRoll": -31.82890183898855,
        "RElbowRoll": 40.81973086301866,
        "RElbowYaw": 0,
        "LShoulderPitch": 70.21831440611889,
        "LShoulderRoll": 45.33112887242689,
        "LElbowRoll": 46.08814933394089,
        "LElbowYaw": 0
    },
    {
        "RShoulderPitch": 72.61366119393834,
        "RShoulderRoll": -31.663460949998385,
        "RElbowRoll": 40.42461834243039,
        "RElbowYaw": 0,
        "LShoulderPitch": 70.74090022919077,
        "LShoulderRoll": 45.10736112166707,
        "LElbowRoll": 45.52046836139286,
        "LElbowYaw": 0
    },
    {
        "RShoulderPitch": 72.96641587498007,
        "RShoulderRoll": -31.75680004127198,
        "RElbowRoll": 40.119977840443795,
        "RElbowYaw": 0,
        "LShoulderPitch": 71.26747663842657,
        "LShoulderRoll": 44.90184395417726,
        "LElbowRoll": 45.16434661847049,
        "LElbowYaw": 0
    },
    {
        "RShoulderPitch": 73.36759356373419,
        "RShoulderRoll": -31.86378313088919,
        "RElbowRoll": 39.658457060947285,
        "RElbowYaw": 0,
        "LShoulderPitch": 71.70703165683598,
        "LShoulderRoll": 44.63221457748956,
        "LElbowRoll": 44.72519686119995,
        "LElbowYaw": 0
    },
    {
        "RShoulderPitch": 74.17521764833026,
        "RShoulderRoll": -31.967792074338156,
        "RElbowRoll": 39.84036747115795,
        "RElbowYaw": 0,
        "LShoulderPitch": 72.38605951035768,
        "LShoulderRoll": 44.15902500785653,
        "LElbowRoll": 44.20889743418465,
        "LElbowYaw": 0
    },
    {
        "RShoulderPitch": 75.47182002410776,
        "RShoulderRoll": -31.145911695981326,
        "RElbowRoll": 39.83045931657085,
        "RElbowYaw": 0,
        "LShoulderPitch": 73.01516573501215,
        "LShoulderRoll": 43.72586292696995,
        "LElbowRoll": 43.4717069799097,
        "LElbowYaw": 0
    },
    {
        "RShoulderPitch": 75.85221561754705,
        "RShoulderRoll": -31.21009807796694,
        "RElbowRoll": 39.52624288011464,
        "RElbowYaw": 0,
        "LShoulderPitch": 73.24665645583443,
        "LShoulderRoll": 43.59246143436669,
        "LElbowRoll": 43.2458486175901,
        "LElbowYaw": 0
    },
    {
        "RShoulderPitch": 76.37202463619245,
        "RShoulderRoll": -31.364759755284624,
        "RElbowRoll": 39.17820359513689,
        "RElbowYaw": 0,
        "LShoulderPitch": 73.72090741048503,
        "LShoulderRoll": 43.34819523678794,
        "LElbowRoll": 42.91410993834671,
        "LElbowYaw": 0
    },
    {
        "RShoulderPitch": 76.56276053253384,
        "RShoulderRoll": -31.445319651258416,
        "RElbowRoll": 40.05661976834165,
        "RElbowYaw": -43.15346046196137,
        "LShoulderPitch": 74.16334646600697,
        "LShoulderRoll": 43.02213327138172,
        "LElbowRoll": 42.400274528443816,
        "LElbowYaw": 0
    },
    {
        "RShoulderPitch": 76.78663885109388,
        "RShoulderRoll": -31.637139560849395,
        "RElbowRoll": 37.68358434558655,
        "RElbowYaw": 0,
        "LShoulderPitch": 74.57222676031488,
        "LShoulderRoll": 42.898541232264535,
        "LElbowRoll": 42.23631271802415,
        "LElbowYaw": 0
    },
    {
        "RShoulderPitch": 77.0535065841909,
        "RShoulderRoll": -31.653748745678453,
        "RElbowRoll": 39.65521068043924,
        "RElbowYaw": -44.19510064580509,
        "LShoulderPitch": 74.85405453716344,
        "LShoulderRoll": 42.65049261169617,
        "LElbowRoll": 41.91037634360552,
        "LElbowYaw": 0
    },
    {
        "RShoulderPitch": 77.32542391031534,
        "RShoulderRoll": -31.703782891339007,
        "RElbowRoll": 36.99208638650629,
        "RElbowYaw": 0,
        "LShoulderPitch": 75.08684318608556,
        "LShoulderRoll": 42.606733636657594,
        "LElbowRoll": 41.87222544699273,
        "LElbowYaw": 0
    },
    {
        "RShoulderPitch": 77.53651517363092,
        "RShoulderRoll": -31.782986538729737,
        "RElbowRoll": 37.30849418199378,
        "RElbowYaw": 0,
        "LShoulderPitch": 75.2001876667982,
        "LShoulderRoll": 42.370585554037035,
        "LElbowRoll": 41.62312714654158,
        "LElbowYaw": 0
    }
]