[
    {
        "RShoulderPitch": 80.20516806747905,
        "RShoulderRoll": -20.03403169221438,
        "RElbowRoll": 30.423179115064613,
        "RElbowYaw": 0,
        "LShoulderPitch": 72.6489809340091,
        "LShoulderRoll": 16.380451357920947,
        "LElbowRoll": 21.185615887857267,
        "LElbowYaw": 0
    },
    {
        "RShoulderPitch": 80.20516806747905,
        "RShoulderRoll": -20.03403169221438,
        "RElbowRoll": 30.423179115064613,
        "RElbowYaw": 0,
        "LShoulderPitch": 72.6489809340091,
        "LShoulderRoll": 16.380451357920947,
        "LElbowRoll": 21.185615887857267,
        "LElbowYaw": 0
    },
    {
        "RShoulderPitch": 80.20516806747905,
        "RShoulderRoll": -20.03403169221438,
        "RElbowRoll": 30.423179115064613,
        "RElbowYaw": 0,
        "LShoulderPitch": 72.6489809340091,
        "LShoulderRoll": 16.380451357920947,
        "LElbowRoll": 21.185615887857267,
        "LElbowYaw": 0
    },
    {
        "RShoulderPitch": 80.20516806747905,
        "RShoulderRoll": -20.03403169221438,
        "RElbowRoll": 30.423179115064613,
        "RElbowYaw": 0,
        "LShoulderPitch": 72.6489809340091,
        "LShoulderRoll": 16.380451357920947,
        "LElbowRoll": 21.185615887857267,
        "LElbowYaw": 0
    },
    {
        "RShoulderPitch": 78.0977703416039,
        "RShoulderRoll": -20.72421220836323,
        "RElbowRoll": 29.67204373207892,
        "RElbowYaw": 0,
        "LShoulderPitch": 72.23730025942821,
        "LShoulderRoll": 16.461946332877154,
        "LElbowRoll": 20.887239054305724,
        "LElbowYaw": 0
    },
    {
        "RShoulderPitch": 78.0977703416039,
        "RShoulderRoll": -20.72421220836323,
        "RElbowRoll": 29.67204373207892,
        "RElbowYaw": 0,
        "LShoulderPitch": 72.23730025942821,
        "LShoulderRoll": 16.461946332877154,
        "LElbowRoll": 20.887239054305724,
        "LElbowYaw": 0
    },
    {
        "RShoulderPitch": 73.31413743558453,
        "RShoulderRoll": -22.244557616069812,
        "RElbowRoll": 26.978817082505998,
        "RElbowYaw": 0,
        "LShoulderPitch": 72.02710329366221,
        "LShoulderRoll": 16.59057005402019,
        "LElbowRoll": 20.894860006159405,
        "LElbowYaw": 0
    },
    {
        "RShoulderPitch": 73.31413743558453,
        "RShoulderRoll": -22.244557616069812,
        "RElbowRoll": 26.978817082505998,
        "RElbowYaw": 0,
        "LShoulderPitch": 72.02710329366221,
        "LShoulderRoll": 16.59057005402019,
        "LElbowRoll": 20.894860006159405,
        "LElbowYaw": 0
    },
    {
        "RShoulderPitch": 73.31413743558453,
        "RShoulderRoll": -22.244557616069812,
        "RElbowRoll": 26.978817082505998,
        "RElbowYaw": 0,
        "LShoulderPitch": 72.02710329366221,
        "LShoulderRoll": 16.59057005402019,
        "LElbowRoll": 20.894860006159405,
        "LElbowYaw": 0
    },
    {
        "RShoulderPitch": 73.31413743558453,
        "RShoulderRoll": -22.244557616069812,
        "RElbowRoll": 26.978817082505998,
        "RElbowYaw": 0,
        "LShoulderPitch": 72.02710329366221,
        "LShoulderRoll": 16.59057005402019,
        "LElbowRoll": 20.894860006159405,
        "LElbowYaw": 0
    },
    {
        "RShoulderPitch": 73.31413743558453,
        "RShoulderRoll": -22.244557616069812,
        "RElbowRoll": 26.978817082505998,
        "RElbowYaw": 0,
        "LShoulderPitch": 72.02710329366221,
        "LShoulderRoll": 16.59057005402019,
        "LElbowRoll": 20.894860006159405,
        "LElbowYaw": 0
    },
    {
        "RShoulderPitch": 73.31413743558453,
        "RShoulderRoll": -22.244557616069812,
        "RElbowRoll": 26.978817082505998,
        "RElbowYaw": 0,
        "LShoulderPitch": 72.02710329366221,
        "LShoulderRoll": 16.59057005402019,
        "LElbowRoll": 20.894860006159405,
        "LElbowYaw": 0
    },
    {
        "RShoulderPitch": 73.31413743558453,
        "RShoulderRoll": -22.244557616069812,
        "RElbowRoll": 26.978817082505998,
        "RElbowYaw": 0,
        "LShoulderPitch": 72.02710329366221,
        "LShoulderRoll": 16.59057005402019,
        "LElbowRoll": 20.894860006159405,
        "LElbowYaw": 0
    },
    {
        "RShoulderPitch": 51.06070928769532,
        "RShoulderRoll": -26.774938970515176,
        "RElbowRoll": 29.57061801614435,
        "RElbowYaw": 0,
        "LShoulderPitch": 71.80661904540993,
        "LShoulderRoll": 16.95782891573599,
        "LElbowRoll": 21.091987797666405,
        "LElbowYaw": 0
    },
    {
        "RShoulderPitch": 51.06070928769532,
        "RShoulderRoll": -26.774938970515176,
        "RElbowRoll": 29.57061801614435,
        "RElbowYaw": 0,
        "LShoulderPitch": 71.80661904540993,
        "LShoulderRoll": 16.95782891573599,
        "LElbowRoll": 21.091987797666405,
        "LElbowYaw": 0
    },
    {
        "RShoulderPitch": 51.06070928769532,
        "RShoulderRoll": -26.774938970515176,
        "RElbowRoll": 29.57061801614435,
        "RElbowYaw": 0,
        "LShoulderPitch": 71.80661904540993,
        "LShoulderRoll": 16.95782891573599,
        "LElbowRoll": 21.091987797666405,
        "LElbowYaw": 0
    },
    {
        "RShoulderPitch": 51.06070928769532,
        "RShoulderRoll": -26.774938970515176,
        "RElbowRoll": 29.57061801614435,
        "RElbowYaw": 0,
        "LShoulderPitch": 71.80661904540993,
        "LShoulderRoll": 16.95782891573599,
        "LElbowRoll": 21.091987797666405,
        "LElbowYaw": 0
    },
    {
        "RShoulderPitch": 51.06070928769532,
        "RShoulderRoll": -26.774938970515176,
        "RElbowRoll": 29.57061801614435,
        "RElbowYaw": 0,
        "LShoulderPitch": 71.80661904540993,
        "LShoulderRoll": 16.95782891573599,
        "LElbowRoll": 21.091987797666405,
        "LElbowYaw": 0
    },
    {
        "RShoulderPitch": 51.06070928769532,
        "RShoulderRoll": -26.774938970515176,
        "RElbowRoll": 29.57061801614435,
        "RElbowYaw": 0,
        "LShoulderPitch": 71.80661904540993,
        "LShoulderRoll": 16.95782891573599,
        "LElbowRoll": 21.091987797666405,
        "LElbowYaw": 0
    },
    {
        "RShoulderPitch": 51.06070928769532,
        "RShoulderRoll": -26.774938970515176,
        "RElbowRoll": 29.57061801614435,
        "RElbowYaw": 0,
        "LShoulderPitch": 71.80661904540993,
        "LShoulderRoll": 16.95782891573599,
        "LElbowRoll": 21.091987797666405,
        "LElbowYaw": 0
    },
    {
        "RShoulderPitch": 51.06070928769532,
        "RShoulderRoll": -26.774938970515176,
        "RElbowRoll": 29.57061801614435,
        "RElbowYaw": 0,
        "LShoulderPitch": 71.80661904540993,
        "LShoulderRoll": 16.95782891573599,
        "LElbowRoll": 21.091987797666405,
        "LElbowYaw": 0
    },
    {
        "RShoulderPitch": 51.06070928769532,
        "RShoulderRoll": -26.774938970515176,
        "RElbowRoll": 29.57061801614435,
        "RElbowYaw": 0,
        "LShoulderPitch": 71.80661904540993,
        "LShoulderRoll": 16.95782891573599,
        "LElbowRoll": 21.091987797666405,
        "LElbowYaw": 0
    },
    {
        "RShoulderPitch": 51.06070928769532,
        "RShoulderRoll": -26.774938970515176,
        "RElbowRoll": 29.57061801614435,
        "RElbowYaw": 0,
        "LShoulderPitch": 71.80661904540993,
        "LShoulderRoll": 16.95782891573599,
        "LElbowRoll": 21.091987797666405,
        "LElbowYaw": 0
    },
    {
        "RShoulderPitch": 51.06070928769532,
        "RShoulderRoll": -26.774938970515176,
        "RElbowRoll": 29.57061801614435,
        "RElbowYaw": 0,
        "LShoulderPitch": 71.80661904540993,
        "LShoulderRoll": 16.95782891573599,
        "LElbowRoll": 21.091987797666405,
        "LElbowYaw": 0
    },
    {
        "RShoulderPitch": 51.06070928769532,
        "RShoulderRoll": -26.774938970515176,
        "RElbowRoll": 29.57061801614435,
        "RElbowYaw": 0,
        "LShoulderPitch": 71.80661904540993,
        "LShoulderRoll": 16.95782891573599,
        "LElbowRoll": 21.091987797666405,
        "LElbowYaw": 0
    },
    {
        "RShoulderPitch": 43.98182628052371,
        "RShoulderRoll": -31.481355116676443,
        "RElbowRoll": 44.25718911639444,
        "RElbowYaw": 0,
        "LShoulderPitch": 72.22013257824909,
        "LShoulderRoll": 17.322369890316825,
        "LElbowRoll": 21.428447827605282,
        "LElbowYaw": 0
    },
    {
        "RShoulderPitch": 42.13266448499625,
        "RShoulderRoll": -37.13609672558578,
        "RElbowRoll": 72.8460925631225,
        "RElbowYaw": 65.72796661904175,
        "LShoulderPitch": 72.04331375641866,
        "LShoulderRoll": 17.77367499102268,
        "LElbowRoll": 21.636524987131338,
        "LElbowYaw": 0
    },
    {
        "RShoulderPitch": 42.13266448499625,
        "RShoulderRoll": -37.13609672558578,
        "RElbowRoll": 72.8460925631225,
        "RElbowYaw": 65.72796661904175,
        "LShoulderPitch": 72.04331375641866,
        "LShoulderRoll": 17.77367499102268,
        "LElbowRoll": 21.636524987131338,
        "LElbowYaw": 0
    },
    {
        "RShoulderPitch": 42.13266448499625,
        "RShoulderRoll": -37.13609672558578,
        "RElbowRoll": 72.8460925631225,
        "RElbowYaw": 65.72796661904175,
        "LShoulderPitch": 72.04331375641866,
        "LShoulderRoll": 17.77367499102268,
        "LElbowRoll": 21.636524987131338,
        "LElbowYaw": 0
    },
    {
        "RShoulderPitch": 42.13266448499625,
        "RShoulderRoll": -37.13609672558578,
        "RElbowRoll": 72.8460925631225,
        "RElbowYaw": 65.72796661904175,
        "LShoulderPitch": 72.04331375641866,
        "LShoulderRoll": 17.77367499102268,
        "LElbowRoll": 21.636524987131338,
        "LElbowYaw": 0
    },
    {
        "RShoulderPitch": 1.40093009245723,
        "RShoulderRoll": -8.517673863761436,
        "RElbowRoll": 23.78249375438193,
        "RElbowYaw": 84.46503792381496,
        "LShoulderPitch": 72.63841603543615,
        "LShoulderRoll": 18.148798842965988,
        "LElbowRoll": 22.299652968064578,
        "LElbowYaw": 0
    },
    {
        "RShoulderPitch": 1.2209228320169103,
        "RShoulderRoll": -7.8100237638465,
        "RElbowRoll": 38.04790900193706,
        "RElbowYaw": 0,
        "LShoulderPitch": 72.81590781809746,
        "LShoulderRoll": 18.156390052824282,
        "LElbowRoll": 22.3476499482814,
        "LElbowYaw": 0
    },
    {
        "RShoulderPitch": 1.2209228320169103,
        "RShoulderRoll": -7.8100237638465,
        "RElbowRoll": 38.04790900193706,
        "RElbowYaw": 0,
        "LShoulderPitch": 72.81590781809746,
        "LShoulderRoll": 18.156390052824282,
        "LElbowRoll": 22.3476499482814,
        "LElbowYaw": 0
    },
    {
        "RShoulderPitch": 1.2209228320169103,
        "RShoulderRoll": -7.8100237638465,
        "RElbowRoll": 38.04790900193706,
        "RElbowYaw": 0,
        "LShoulderPitch": 72.81590781809746,
        "LShoulderRoll": 18.156390052824282,
        "LElbowRoll": 22.3476499482814,
        "LElbowYaw": 0
    },
    {
        "RShoulderPitch": 1.2209228320169103,
        "RShoulderRoll": -7.8100237638465,
        "RElbowRoll": 38.04790900193706,
        "RElbowYaw": 0,
        "LShoulderPitch": 72.81590781809746,
        "LShoulderRoll": 18.156390052824282,
        "LElbowRoll": 22.3476499482814,
        "LElbowYaw": 0
    },
    {
        "RShoulderPitch": 1.2209228320169103,
        "RShoulderRoll": -7.8100237638465,
        "RElbowRoll": 38.04790900193706,
        "RElbowYaw": 0,
        "LShoulderPitch": 72.81590781809746,
        "LShoulderRoll": 18.156390052824282,
        "LElbowRoll": 22.3476499482814,
        "LElbowYaw": 0
    },
    {
        "RShoulderPitch": 1.2209228320169103,
        "RShoulderRoll": -7.8100237638465,
        "RElbowRoll": 38.04790900193706,
        "RElbowYaw": 0,
        "LShoulderPitch": 72.81590781809746,
        "LShoulderRoll": 18.156390052824282,
        "LElbowRoll": 22.3476499482814,
        "LElbowYaw": 0
    },
    {
        "RShoulderPitch": 0.7297827712130527,
        "RShoulderRoll": 10.514702006531996,
        "RElbowRoll": 28.65098664568646,
        "RElbowYaw": 0,
        "LShoulderPitch": 72.94382839250987,
        "LShoulderRoll": 18.75820879088217,
        "LElbowRoll": 22.571613128075626,
        "LElbowYaw": 0
    },
    {
        "RShoulderPitch": 0.7297827712130527,
        "RShoulderRoll": 10.514702006531996,
        "RElbowRoll": 28.65098664568646,
        "RElbowYaw": 0,
        "LShoulderPitch": 72.94382839250987,
        "LShoulderRoll": 18.75820879088217,
        "LElbowRoll": 22.571613128075626,
        "LElbowYaw": 0
    },
    {
        "RShoulderPitch": 0.7297827712130527,
        "RShoulderRoll": 10.514702006531996,
        "RElbowRoll": 28.65098664568646,
        "RElbowYaw": 0,
        "LShoulderPitch": 72.94382839250987,
        "LShoulderRoll": 18.75820879088217,
        "LElbowRoll": 22.571613128075626,
        "LElbowYaw": 0
    },
    {
        "RShoulderPitch": 0.7297827712130527,
        "RShoulderRoll": 10.514702006531996,
        "RElbowRoll": 28.65098664568646,
        "RElbowYaw": 0,
        "LShoulderPitch": 72.94382839250987,
        "LShoulderRoll": 18.75820879088217,
        "LElbowRoll": 22.571613128075626,
        "LElbowYaw": 0
    },
    {
        "RShoulderPitch": 0.7297827712130527,
        "RShoulderRoll": 10.514702006531996,
        "RElbowRoll": 28.65098664568646,
        "RElbowYaw": 0,
        "LShoulderPitch": 72.94382839250987,
        "LShoulderRoll": 18.75820879088217,
        "LElbowRoll": 22.571613128075626,
        "LElbowYaw": 0
    },
    {
        "RShoulderPitch": 0.7297827712130527,
        "RShoulderRoll": 10.514702006531996,
        "RElbowRoll": 28.65098664568646,
        "RElbowYaw": 0,
        "LShoulderPitch": 72.94382839250987,
        "LShoulderRoll": 18.75820879088217,
        "LElbowRoll": 22.571613128075626,
        "LElbowYaw": 0
    },
    {
        "RShoulderPitch": 0.7297827712130527,
        "RShoulderRoll": 10.514702006531996,
        "RElbowRoll": 28.65098664568646,
        "RElbowYaw": 0,
        "LShoulderPitch": 72.94382839250987,
        "LShoulderRoll": 18.75820879088217,
        "LElbowRoll": 22.571613128075626,
        "LElbowYaw": 0
    },
    {
        "RShoulderPitch": 0.7297827712130527,
        "RShoulderRoll": 10.514702006531996,
        "RElbowRoll": 28.65098664568646,
        "RElbowYaw": 0,
        "LShoulderPitch": 72.94382839250987,
        "LShoulderRoll": 18.75820879088217,
        "LElbowRoll": 22.571613128075626,
        "LElbowYaw": 0
    },
    {
        "RShoulderPitch": 0.7297827712130527,
        "RShoulderRoll": 10.514702006531996,
        "RElbowRoll": 28.65098664568646,
        "RElbowYaw": 0,
        "LShoulderPitch": 72.94382839250987,
        "LShoulderRoll": 18.75820879088217,
        "LElbowRoll": 22.571613128075626,
        "LElbowYaw": 0
    },
    {
        "RShoulderPitch": 0.7297827712130527,
        "RShoulderRoll": 10.514702006531996,
        "RElbowRoll": 28.65098664568646,
        "RElbowYaw": 0,
        "LShoulderPitch": 72.94382839250987,
        "LShoulderRoll": 18.75820879088217,
        "LElbowRoll": 22.571613128075626,
        "LElbowYaw": 0
    },
    {
        "RShoulderPitch": 0.7297827712130527,
        "RShoulderRoll": 10.514702006531996,
        "RElbowRoll": 28.65098664568646,
        "RElbowYaw": 0,
        "LShoulderPitch": 72.94382839250987,
        "LShoulderRoll": 18.75820879088217,
        "LElbowRoll": 22.571613128075626,
        "LElbowYaw": 0
    },
    {
        "RShoulderPitch": 0.7297827712130527,
        "RShoulderRoll": 10.514702006531996,
        "RElbowRoll": 28.65098664568646,
        "RElbowYaw": 0,
        "LShoulderPitch": 72.94382839250987,
        "LShoulderRoll": 18.75820879088217,
        "LElbowRoll": 22.571613128075626,
        "LElbowYaw": 0
    },
    {
        "RShoulderPitch": 0.7297827712130527,
        "RShoulderRoll": 10.514702006531996,
        "RElbowRoll": 28.65098664568646,
        "RElbowYaw": 0,
        "LShoulderPitch": 72.94382839250987,
        "LShoulderRoll": 18.75820879088217,
        "LElbowRoll": 22.571613128075626,
        "LElbowYaw": 0
    },
    {
        "RShoulderPitch": -8.948661214059458,
        "RShoulderRoll": 27.663763793153283,
        "RElbowRoll": 67.61435655615398,
        "RElbowYaw": 0,
        "LShoulderPitch": 73.17605801037416,
        "LShoulderRoll": 17.061964431157463,
        "LElbowRoll": 21.09656561321637,
        "LElbowYaw": 0
    },
    {
        "RShoulderPitch": -9.640722864211295,
        "RShoulderRoll": 27.149299314411635,
        "RElbowRoll": 68.8132097348405,
        "RElbowYaw": 0,
        "LShoulderPitch": 74.01307111046418,
        "LShoulderRoll": 16.118661494606226,
        "LElbowRoll": 20.85746144084115,
        "LElbowYaw": 0
    },
    {
        "RShoulderPitch": -10.083686675462344,
        "RShoulderRoll": 27.104513075568445,
        "RElbowRoll": 72.22696071317962,
        "RElbowYaw": 0,
        "LShoulderPitch": 74.8199763829867,
        "LShoulderRoll": 14.967395066876056,
        "LElbowRoll": 21.019883744942916,
        "LElbowYaw": 101.32380490902182
    },
    {
        "RShoulderPitch": -10.083686675462344,
        "RShoulderRoll": 27.104513075568445,
        "RElbowRoll": 72.22696071317962,
        "RElbowYaw": 0,
        "LShoulderPitch": 74.8199763829867,
        "LShoulderRoll": 14.967395066876056,
        "LElbowRoll": 21.019883744942916,
        "LElbowYaw": 101.32380490902182
    },
    {
        "RShoulderPitch": -10.083686675462344,
        "RShoulderRoll": 27.104513075568445,
        "RElbowRoll": 72.22696071317962,
        "RElbowYaw": 0,
        "LShoulderPitch": 74.8199763829867,
        "LShoulderRoll": 14.967395066876056,
        "LElbowRoll": 21.019883744942916,
        "LElbowYaw": 101.32380490902182
    },
    {
        "RShoulderPitch": -10.083686675462344,
        "RShoulderRoll": 27.104513075568445,
        "RElbowRoll": 72.22696071317962,
        "RElbowYaw": 0,
        "LShoulderPitch": 74.8199763829867,
        "LShoulderRoll": 14.967395066876056,
        "LElbowRoll": 21.019883744942916,
        "LElbowYaw": 101.32380490902182
    },
    {
        "RShoulderPitch": -11.075258479255874,
        "RShoulderRoll": 27.831658482534312,
        "RElbowRoll": 77.12137550660613,
        "RElbowYaw": 0,
        "LShoulderPitch": 74.59597309927919,
        "LShoulderRoll": 14.822932068237323,
        "LElbowRoll": 22.442735602936096,
        "LElbowYaw": 100.94370734837645
    },
    {
        "RShoulderPitch": -11.583155275290341,
        "RShoulderRoll": 28.021642921808926,
        "RElbowRoll": 69.96590720383877,
        "RElbowYaw": 0,
        "LShoulderPitch": 77.24766289164687,
        "LShoulderRoll": 13.167122508485573,
        "LElbowRoll": 22.67974961329017,
        "LElbowYaw": 103.55647915348639
    },
    {
        "RShoulderPitch": -11.583155275290341,
        "RShoulderRoll": 28.021642921808926,
        "RElbowRoll": 69.96590720383877,
        "RElbowYaw": 0,
        "LShoulderPitch": 77.24766289164687,
        "LShoulderRoll": 13.167122508485573,
        "LElbowRoll": 22.67974961329017,
        "LElbowYaw": 103.55647915348639
    },
    {
        "RShoulderPitch": -11.583155275290341,
        "RShoulderRoll": 28.021642921808926,
        "RElbowRoll": 69.96590720383877,
        "RElbowYaw": 0,
        "LShoulderPitch": 77.24766289164687,
        "LShoulderRoll": 13.167122508485573,
        "LElbowRoll": 22.67974961329017,
        "LElbowYaw": 103.55647915348639
    },
    {
        "RShoulderPitch": -11.583155275290341,
        "RShoulderRoll": 28.021642921808926,
        "RElbowRoll": 69.96590720383877,
        "RElbowYaw": 0,
        "LShoulderPitch": 77.24766289164687,
        "LShoulderRoll": 13.167122508485573,
        "LElbowRoll": 22.67974961329017,
        "LElbowYaw": 103.55647915348639
    },
    {
        "RShoulderPitch": -11.583155275290341,
        "RShoulderRoll": 28.021642921808926,
        "RElbowRoll": 69.96590720383877,
        "RElbowYaw": 0,
        "LShoulderPitch": 77.24766289164687,
        "LShoulderRoll": 13.167122508485573,
        "LElbowRoll": 22.67974961329017,
        "LElbowYaw": 103.55647915348639
    },
    {
        "RShoulderPitch": -11.583155275290341,
        "RShoulderRoll": 28.021642921808926,
        "RElbowRoll": 69.96590720383877,
        "RElbowYaw": 0,
        "LShoulderPitch": 77.24766289164687,
        "LShoulderRoll": 13.167122508485573,
        "LElbowRoll": 22.67974961329017,
        "LElbowYaw": 103.55647915348639
    },
    {
        "RShoulderPitch": -11.911034562876647,
        "RShoulderRoll": 28.297626436504324,
        "RElbowRoll": 70.35817106195634,
        "RElbowYaw": 0,
        "LShoulderPitch": 78.45379590031881,
        "LShoulderRoll": 12.48176590929614,
        "LElbowRoll": 23.050119388885292,
        "LElbowYaw": 104.70479799137104
    },
    {
        "RShoulderPitch": -11.911034562876647,
        "RShoulderRoll": 28.297626436504324,
        "RElbowRoll": 70.35817106195634,
        "RElbowYaw": 0,
        "LShoulderPitch": 78.45379590031881,
        "LShoulderRoll": 12.48176590929614,
        "LElbowRoll": 23.050119388885292,
        "LElbowYaw": 104.70479799137104
    },
    {
        "RShoulderPitch": -11.911034562876647,
        "RShoulderRoll": 28.297626436504324,
        "RElbowRoll": 70.35817106195634,
        "RElbowYaw": 0,
        "LShoulderPitch": 78.45379590031881,
        "LShoulderRoll": 12.48176590929614,
        "LElbowRoll": 23.050119388885292,
        "LElbowYaw": 104.70479799137104
    },
    {
        "RShoulderPitch": -11.911034562876647,
        "RShoulderRoll": 28.297626436504324,
        "RElbowRoll": 70.35817106195634,
        "RElbowYaw": 0,
        "LShoulderPitch": 78.45379590031881,
        "LShoulderRoll": 12.48176590929614,
        "LElbowRoll": 23.050119388885292,
        "LElbowYaw": 104.70479799137104
    },
    {
        "RShoulderPitch": -11.834467391890191,
        "RShoulderRoll": 28.414887961738483,
        "RElbowRoll": 70.93633070249157,
        "RElbowYaw": 0,
        "LShoulderPitch": 79.29806574309242,
        "LShoulderRoll": 12.513728724736746,
        "LElbowRoll": 23.57809009415692,
        "LElbowYaw": 105.57612991021826
    },
    {
        "RShoulderPitch": -11.834467391890191,
        "RShoulderRoll": 28.414887961738483,
        "RElbowRoll": 70.93633070249157,
        "RElbowYaw": 0,
        "LShoulderPitch": 79.29806574309242,
        "LShoulderRoll": 12.513728724736746,
        "LElbowRoll": 23.57809009415692,
        "LElbowYaw": 105.57612991021826
    },
    {
        "RShoulderPitch": -11.834467391890191,
        "RShoulderRoll": 28.414887961738483,
        "RElbowRoll": 70.93633070249157,
        "RElbowYaw": 0,
        "LShoulderPitch": 79.29806574309242,
        "LShoulderRoll": 12.513728724736746,
        "LElbowRoll": 23.57809009415692,
        "LElbowYaw": 105.57612991021826
    },
    {
        "RShoulderPitch": -11.834467391890191,
        "RShoulderRoll": 28.414887961738483,
        "RElbowRoll": 70.93633070249157,
        "RElbowYaw": 0,
        "LShoulderPitch": 79.29806574309242,
        "LShoulderRoll": 12.513728724736746,
        "LElbowRoll": 23.57809009415692,
        "LElbowYaw": 105.57612991021826
    },
    {
        "RShoulderPitch": -11.834467391890191,
        "RShoulderRoll": 28.414887961738483,
        "RElbowRoll": 70.93633070249157,
        "RElbowYaw": 0,
        "LShoulderPitch": 79.29806574309242,
        "LShoulderRoll": 12.513728724736746,
        "LElbowRoll": 23.57809009415692,
        "LElbowYaw": 105.57612991021826
    },
    {
        "RShoulderPitch": -11.935697761473415,
        "RShoulderRoll": 28.696419828330733,
        "RElbowRoll": 78.64806556679618,
        "RElbowYaw": 0,
        "LShoulderPitch": 78.98321164427519,
        "LShoulderRoll": 12.617558594764352,
        "LElbowRoll": 23.371959546717875,
        "LElbowYaw": 105.30917763735789
    },
    {
        "RShoulderPitch": -12.004993299154624,
        "RShoulderRoll": 28.99626358789377,
        "RElbowRoll": 78.86879496698116,
        "RElbowYaw": 0,
        "LShoulderPitch": 78.74884343969958,
        "LShoulderRoll": 12.752726899062624,
        "LElbowRoll": 23.23093718728657,
        "LElbowYaw": 105.12565632749333
    },
    {
        "RShoulderPitch": -12.004993299154624,
        "RShoulderRoll": 28.99626358789377,
        "RElbowRoll": 78.86879496698116,
        "RElbowYaw": 0,
        "LShoulderPitch": 78.74884343969958,
        "LShoulderRoll": 12.752726899062624,
        "LElbowRoll": 23.23093718728657,
        "LElbowYaw": 105.12565632749333
    },
    {
        "RShoulderPitch": -12.004993299154624,
        "RShoulderRoll": 28.99626358789377,
        "RElbowRoll": 78.86879496698116,
        "RElbowYaw": 0,
        "LShoulderPitch": 78.74884343969958,
        "LShoulderRoll": 12.752726899062624,
        "LElbowRoll": 23.23093718728657,
        "LElbowYaw": 105.12565632749333
    },
    {
        "RShoulderPitch": -12.038435362613365,
        "RShoulderRoll": 29.22844688467343,
        "RElbowRoll": 78.56193971973562,
        "RElbowYaw": 0,
        "LShoulderPitch": 78.5103138443455,
        "LShoulderRoll": 12.898321915657073,
        "LElbowRoll": 23.00410687992641,
        "LElbowYaw": 104.88114112689763
    },
    {
        "RShoulderPitch": -12.084786674835293,
        "RShoulderRoll": 29.318985273564817,
        "RElbowRoll": 78.55706230386835,
        "RElbowYaw": 0,
        "LShoulderPitch": 78.24562740909646,
        "LShoulderRoll": 13.028504151432426,
        "LElbowRoll": 22.75591549709631,
        "LElbowYaw": 104.57291344966298
    },
    {
        "RShoulderPitch": -12.14220650927742,
        "RShoulderRoll": 29.404259778309484,
        "RElbowRoll": 83.44705573815611,
        "RElbowYaw": 0,
        "LShoulderPitch": 77.99236914758461,
        "LShoulderRoll": 13.292900387208038,
        "LElbowRoll": 22.038309765169316,
        "LElbowYaw": 0
    },
    {
        "RShoulderPitch": -12.14220650927742,
        "RShoulderRoll": 29.404259778309484,
        "RElbowRoll": 83.44705573815611,
        "RElbowYaw": 0,
        "LShoulderPitch": 77.99236914758461,
        "LShoulderRoll": 13.292900387208038,
        "LElbowRoll": 22.038309765169316,
        "LElbowYaw": 0
    },
    {
        "RShoulderPitch": -12.14220650927742,
        "RShoulderRoll": 29.404259778309484,
        "RElbowRoll": 83.44705573815611,
        "RElbowYaw": 0,
        "LShoulderPitch": 77.99236914758461,
        "LShoulderRoll": 13.292900387208038,
        "LElbowRoll": 22.038309765169316,
        "LElbowYaw": 0
    },
    {
        "RShoulderPitch": -12.14220650927742,
        "RShoulderRoll": 29.404259778309484,
        "RElbowRoll": 83.44705573815611,
        "RElbowYaw": 0,
        "LShoulderPitch": 77.99236914758461,
        "LShoulderRoll": 13.292900387208038,
        "LElbowRoll": 22.038309765169316,
        "LElbowYaw": 0
    },
    {
        "RShoulderPitch": -12.115799411951382,
        "RShoulderRoll": 29.34675893418355,
        "RElbowRoll": 83.46217360986081,
        "RElbowYaw": 0,
        "LShoulderPitch": 77.84098786588198,
        "LShoulderRoll": 13.316010045445795,
        "LElbowRoll": 21.604888858820516,
        "LElbowYaw": 0
    },
    {
        "RShoulderPitch": -12.115799411951382,
        "RShoulderRoll": 29.34675893418355,
        "RElbowRoll": 83.46217360986081,
        "RElbowYaw": 0,
        "LShoulderPitch": 77.84098786588198,
        "LShoulderRoll": 13.316010045445795,
        "LElbowRoll": 21.604888858820516,
        "LElbowYaw": 0
    },
    {
        "RShoulderPitch": -12.115799411951382,
        "RShoulderRoll": 29.34675893418355,
        "RElbowRoll": 83.46217360986081,
        "RElbowYaw": 0,
        "LShoulderPitch": 77.84098786588198,
        "LShoulderRoll": 13.316010045445795,
        "LElbowRoll": 21.604888858820516,
        "LElbowYaw": 0
    },
    {
        "RShoulderPitch": -12.115799411951382,
        "RShoulderRoll": 29.34675893418355,
        "RElbowRoll": 83.46217360986081,
        "RElbowYaw": 0,
        "LShoulderPitch": 77.84098786588198,
        "LShoulderRoll": 13.316010045445795,
        "LElbowRoll": 21.604888858820516,
        "LElbowYaw": 0
    },
    {
        "RShoulderPitch": -12.115799411951382,
        "RShoulderRoll": 29.34675893418355,
        "RElbowRoll": 83.46217360986081,
        "RElbowYaw": 0,
        "LShoulderPitch": 77.84098786588198,
        "LShoulderRoll": 13.316010045445795,
        "LElbowRoll": 21.604888858820516,
        "LElbowYaw": 0
    },
    {
        "RShoulderPitch": -11.218551576030748,
        "RShoulderRoll": 27.93594224703641,
        "RElbowRoll": 66.4917474650445,
        "RElbowYaw": 0,
        "LShoulderPitch": 77.28188805825094,
        "LShoulderRoll": 13.652135006653278,
        "LElbowRoll": 21.464980986307296,
        "LElbowYaw": 0
    },
    {
        "RShoulderPitch": -11.218551576030748,
        "RShoulderRoll": 27.93594224703641,
        "RElbowRoll": 66.4917474650445,
        "RElbowYaw": 0,
        "LShoulderPitch": 77.28188805825094,
        "LShoulderRoll": 13.652135006653278,
        "LElbowRoll": 21.464980986307296,
        "LElbowYaw": 0
    },
    {
        "RShoulderPitch": -10.507947818721767,
        "RShoulderRoll": 27.02211605041834,
        "RElbowRoll": 73.99470047922352,
        "RElbowYaw": 0,
        "LShoulderPitch": 77.04367738672484,
        "LShoulderRoll": 13.79439200971866,
        "LElbowRoll": 21.366972205287453,
        "LElbowYaw": 103.40707346965334
    },
    {
        "RShoulderPitch": -10.243843258358044,
        "RShoulderRoll": 26.221692937894815,
        "RElbowRoll": 73.34785060713577,
        "RElbowYaw": 0,
        "LShoulderPitch": 76.64990431155196,
        "LShoulderRoll": 13.879715501495797,
        "LElbowRoll": 21.03288997766066,
        "LElbowYaw": 0
    },
    {
        "RShoulderPitch": -10.243843258358044,
        "RShoulderRoll": 26.221692937894815,
        "RElbowRoll": 73.34785060713577,
        "RElbowYaw": 0,
        "LShoulderPitch": 76.64990431155196,
        "LShoulderRoll": 13.879715501495797,
        "LElbowRoll": 21.03288997766066,
        "LElbowYaw": 0
    },
    {
        "RShoulderPitch": -9.74905149870359,
        "RShoulderRoll": 24.491979970767634,
        "RElbowRoll": 70.53536146034293,
        "RElbowYaw": 0,
        "LShoulderPitch": 76.31261746104664,
        "LShoulderRoll": 14.069679907319715,
        "LElbowRoll": 20.915945904362616,
        "LElbowYaw": 0
    },
    {
        "RShoulderPitch": -9.805402258832157,
        "RShoulderRoll": 23.02402544276157,
        "RElbowRoll": 61.61705056461102,
        "RElbowYaw": 0,
        "LShoulderPitch": 76.06160077996391,
        "LShoulderRoll": 14.246885827865697,
        "LElbowRoll": 20.78079040729031,
        "LElbowYaw": 0
    },
    {
        "RShoulderPitch": -9.805402258832157,
        "RShoulderRoll": 23.02402544276157,
        "RElbowRoll": 61.61705056461102,
        "RElbowYaw": 0,
        "LShoulderPitch": 76.06160077996391,
        "LShoulderRoll": 14.246885827865697,
        "LElbowRoll": 20.78079040729031,
        "LElbowYaw": 0
    },
    {
        "RShoulderPitch": -9.805402258832157,
        "RShoulderRoll": 23.02402544276157,
        "RElbowRoll": 61.61705056461102,
        "RElbowYaw": 0,
        "LShoulderPitch": 76.06160077996391,
        "LShoulderRoll": 14.246885827865697,
        "LElbowRoll": 20.78079040729031,
        "LElbowYaw": 0
    },
    {
        "RShoulderPitch": -9.805402258832157,
        "RShoulderRoll": 23.02402544276157,
        "RElbowRoll": 61.61705056461102,
        "RElbowYaw": 0,
        "LShoulderPitch": 76.06160077996391,
        "LShoulderRoll": 14.246885827865697,
        "LElbowRoll": 20.78079040729031,
        "LElbowYaw": 0
    },
    {
        "RShoulderPitch": -9.805402258832157,
        "RShoulderRoll": 23.02402544276157,
        "RElbowRoll": 61.61705056461102,
        "RElbowYaw": 0,
        "LShoulderPitch": 76.06160077996391,
        "LShoulderRoll": 14.246885827865697,
        "LElbowRoll": 20.78079040729031,
        "LElbowYaw": 0
    },
    {
        "RShoulderPitch": -9.472536857803581,
        "RShoulderRoll": 18.038940238115853,
        "RElbowRoll": 53.77556426374443,
        "RElbowYaw": 0,
        "LShoulderPitch": 75.8652039364942,
        "LShoulderRoll": 14.693942912525458,
        "LElbowRoll": 20.73447493553587,
        "LElbowYaw": 0
    },
    {
        "RShoulderPitch": -9.16292175050968,
        "RShoulderRoll": 14.607781608276671,
        "RElbowRoll": 51.682096754643624,
        "RElbowYaw": 0,
        "LShoulderPitch": 75.79878024881778,
        "LShoulderRoll": 15.09012641945974,
        "LElbowRoll": 20.83551627931206,
        "LElbowYaw": 0
    },
    {
        "RShoulderPitch": -8.785844394244508,
        "RShoulderRoll": 11.275890043456352,
        "RElbowRoll": 52.85772652515686,
        "RElbowYaw": 0,
        "LShoulderPitch": 75.83358435502825,
        "LShoulderRoll": 15.712295056351659,
        "LElbowRoll": 21.20077780684656,
        "LElbowYaw": 0
    },
    {
        "RShoulderPitch": -8.785844394244508,
        "RShoulderRoll": 11.275890043456352,
        "RElbowRoll": 52.85772652515686,
        "RElbowYaw": 0,
        "LShoulderPitch": 75.83358435502825,
        "LShoulderRoll": 15.712295056351659,
        "LElbowRoll": 21.20077780684656,
        "LElbowYaw": 0
    },
    {
        "RShoulderPitch": -8.785844394244508,
        "RShoulderRoll": 11.275890043456352,
        "RElbowRoll": 52.85772652515686,
        "RElbowYaw": 0,
        "LShoulderPitch": 75.83358435502825,
        "LShoulderRoll": 15.712295056351659,
        "LElbowRoll": 21.20077780684656,
        "LElbowYaw": 0
    },
    {
        "RShoulderPitch": -8.785844394244508,
        "RShoulderRoll": 11.275890043456352,
        "RElbowRoll": 52.85772652515686,
        "RElbowYaw": 0,
        "LShoulderPitch": 75.83358435502825,
        "LShoulderRoll": 15.712295056351659,
        "LElbowRoll": 21.20077780684656,
        "LElbowYaw": 0
    },
    {
        "RShoulderPitch": -8.785844394244508,
        "RShoulderRoll": 11.275890043456352,
        "RElbowRoll": 52.85772652515686,
        "RElbowYaw": 0,
        "LShoulderPitch": 75.83358435502825,
        "LShoulderRoll": 15.712295056351659,
        "LElbowRoll": 21.20077780684656,
        "LElbowYaw": 0
    },
    {
        "RShoulderPitch": -4.385632617084537,
        "RShoulderRoll": 2.3981992415541966,
        "RElbowRoll": 42.27747293239645,
        "RElbowYaw": 0,
        "LShoulderPitch": 75.68650343684094,
        "LShoulderRoll": 16.070175143879283,
        "LElbowRoll": 21.40402505352114,
        "LElbowYaw": 0
    },
    {
        "RShoulderPitch": -4.385632617084537,
        "RShoulderRoll": 2.3981992415541966,
        "RElbowRoll": 42.27747293239645,
        "RElbowYaw": 0,
        "LShoulderPitch": 75.68650343684094,
        "LShoulderRoll": 16.070175143879283,
        "LElbowRoll": 21.40402505352114,
        "LElbowYaw": 0
    },
    {
        "RShoulderPitch": -4.385632617084537,
        "RShoulderRoll": 2.3981992415541966,
        "RElbowRoll": 42.27747293239645,
        "RElbowYaw": 0,
        "LShoulderPitch": 75.68650343684094,
        "LShoulderRoll": 16.070175143879283,
        "LElbowRoll": 21.40402505352114,
        "LElbowYaw": 0
    },
    {
        "RShoulderPitch": -2.38326262755326,
        "RShoulderRoll": 0.8085659263395516,
        "RElbowRoll": 35.01631291244027,
        "RElbowYaw": 0,
        "LShoulderPitch": 75.67740048366517,
        "LShoulderRoll": 16.732247623505707,
        "LElbowRoll": 22.075152178522615,
        "LElbowYaw": 0
    },
    {
        "RShoulderPitch": -2.38326262755326,
        "RShoulderRoll": 0.8085659263395516,
        "RElbowRoll": 35.01631291244027,
        "RElbowYaw": 0,
        "LShoulderPitch": 75.67740048366517,
        "LShoulderRoll": 16.732247623505707,
        "LElbowRoll": 22.075152178522615,
        "LElbowYaw": 0
    },
    {
        "RShoulderPitch": -2.38326262755326,
        "RShoulderRoll": 0.8085659263395516,
        "RElbowRoll": 35.01631291244027,
        "RElbowYaw": 0,
        "LShoulderPitch": 75.67740048366517,
        "LShoulderRoll": 16.732247623505707,
        "LElbowRoll": 22.075152178522615,
        "LElbowYaw": 0
    },
    {
        "RShoulderPitch": -2.38326262755326,
        "RShoulderRoll": 0.8085659263395516,
        "RElbowRoll": 35.01631291244027,
        "RElbowYaw": 0,
        "LShoulderPitch": 75.67740048366517,
        "LShoulderRoll": 16.732247623505707,
        "LElbowRoll": 22.075152178522615,
        "LElbowYaw": 0
    },
    {
        "RShoulderPitch": -2.38326262755326,
        "RShoulderRoll": 0.8085659263395516,
        "RElbowRoll": 35.01631291244027,
        "RElbowYaw": 0,
        "LShoulderPitch": 75.67740048366517,
        "LShoulderRoll": 16.732247623505707,
        "LElbowRoll": 22.075152178522615,
        "LElbowYaw": 0
    },
    {
        "RShoulderPitch": 5.319048665202899,
        "RShoulderRoll": -5.835648267658751,
        "RElbowRoll": 38.14070471552864,
        "RElbowYaw": 74.9817687792158,
        "LShoulderPitch": 75.70238698930665,
        "LShoulderRoll": 17.862238030339892,
        "LElbowRoll": 22.79430566561274,
        "LElbowYaw": 0
    },
    {
        "RShoulderPitch": 5.319048665202899,
        "RShoulderRoll": -5.835648267658751,
        "RElbowRoll": 38.14070471552864,
        "RElbowYaw": 74.9817687792158,
        "LShoulderPitch": 75.70238698930665,
        "LShoulderRoll": 17.862238030339892,
        "LElbowRoll": 22.79430566561274,
        "LElbowYaw": 0
    },
    {
        "RShoulderPitch": 5.319048665202899,
        "RShoulderRoll": -5.835648267658751,
        "RElbowRoll": 38.14070471552864,
        "RElbowYaw": 74.9817687792158,
        "LShoulderPitch": 75.70238698930665,
        "LShoulderRoll": 17.862238030339892,
        "LElbowRoll": 22.79430566561274,
        "LElbowYaw": 0
    },
    {
        "RShoulderPitch": 5.319048665202899,
        "RShoulderRoll": -5.835648267658751,
        "RElbowRoll": 38.14070471552864,
        "RElbowYaw": 74.9817687792158,
        "LShoulderPitch": 75.70238698930665,
        "LShoulderRoll": 17.862238030339892,
        "LElbowRoll": 22.79430566561274,
        "LElbowYaw": 0
    },
    {
        "RShoulderPitch": 5.319048665202899,
        "RShoulderRoll": -5.835648267658751,
        "RElbowRoll": 38.14070471552864,
        "RElbowYaw": 74.9817687792158,
        "LShoulderPitch": 75.70238698930665,
        "LShoulderRoll": 17.862238030339892,
        "LElbowRoll": 22.79430566561274,
        "LElbowYaw": 0
    },
    {
        "RShoulderPitch": 5.319048665202899,
        "RShoulderRoll": -5.835648267658751,
        "RElbowRoll": 38.14070471552864,
        "RElbowYaw": 74.9817687792158,
        "LShoulderPitch": 75.70238698930665,
        "LShoulderRoll": 17.862238030339892,
        "LElbowRoll": 22.79430566561274,
        "LElbowYaw": 0
    },
    {
        "RShoulderPitch": 5.319048665202899,
        "RShoulderRoll": -5.835648267658751,
        "RElbowRoll": 38.14070471552864,
        "RElbowYaw": 74.9817687792158,
        "LShoulderPitch": 75.70238698930665,
        "LShoulderRoll": 17.862238030339892,
        "LElbowRoll": 22.79430566561274,
        "LElbowYaw": 0
    },
    {
        "RShoulderPitch": 5.319048665202899,
        "RShoulderRoll": -5.835648267658751,
        "RElbowRoll": 38.14070471552864,
        "RElbowYaw": 74.9817687792158,
        "LShoulderPitch": 75.70238698930665,
        "LShoulderRoll": 17.862238030339892,
        "LElbowRoll": 22.79430566561274,
        "LElbowYaw": 0
    },
    {
        "RShoulderPitch": 5.319048665202899,
        "RShoulderRoll": -5.835648267658751,
        "RElbowRoll": 38.14070471552864,
        "RElbowYaw": 74.9817687792158,
        "LShoulderPitch": 75.70238698930665,
        "LShoulderRoll": 17.862238030339892,
        "LElbowRoll": 22.79430566561274,
        "LElbowYaw": 0
    },
    {
        "RShoulderPitch": 5.319048665202899,
        "RShoulderRoll": -5.835648267658751,
        "RElbowRoll": 38.14070471552864,
        "RElbowYaw": 74.9817687792158,
        "LShoulderPitch": 75.70238698930665,
        "LShoulderRoll": 17.862238030339892,
        "LElbowRoll": 22.79430566561274,
        "LElbowYaw": 0
    },
    {
        "RShoulderPitch": 37.92491325573539,
        "RShoulderRoll": -18.64258587523276,
        "RElbowRoll": 24.167505427469536,
        "RElbowYaw": 0,
        "LShoulderPitch": 75.76204192775172,
        "LShoulderRoll": 17.90519328209561,
        "LElbowRoll": 22.95977950425896,
        "LElbowYaw": 0
    },
    {
        "RShoulderPitch": 37.92491325573539,
        "RShoulderRoll": -18.64258587523276,
        "RElbowRoll": 24.167505427469536,
        "RElbowYaw": 0,
        "LShoulderPitch": 75.76204192775172,
        "LShoulderRoll": 17.90519328209561,
        "LElbowRoll": 22.95977950425896,
        "LElbowYaw": 0
    },
    {
        "RShoulderPitch": 37.92491325573539,
        "RShoulderRoll": -18.64258587523276,
        "RElbowRoll": 24.167505427469536,
        "RElbowYaw": 0,
        "LShoulderPitch": 75.76204192775172,
        "LShoulderRoll": 17.90519328209561,
        "LElbowRoll": 22.95977950425896,
        "LElbowYaw": 0
    },
    {
        "RShoulderPitch": 37.92491325573539,
        "RShoulderRoll": -18.64258587523276,
        "RElbowRoll": 24.167505427469536,
        "RElbowYaw": 0,
        "LShoulderPitch": 75.76204192775172,
        "LShoulderRoll": 17.90519328209561,
        "LElbowRoll": 22.95977950425896,
        "LElbowYaw": 0
    },
    {
        "RShoulderPitch": 37.92491325573539,
        "RShoulderRoll": -18.64258587523276,
        "RElbowRoll": 24.167505427469536,
        "RElbowYaw": 0,
        "LShoulderPitch": 75.76204192775172,
        "LShoulderRoll": 17.90519328209561,
        "LElbowRoll": 22.95977950425896,
        "LElbowYaw": 0
    },
    {
        "RShoulderPitch": 37.92491325573539,
        "RShoulderRoll": -18.64258587523276,
        "RElbowRoll": 24.167505427469536,
        "RElbowYaw": 0,
        "LShoulderPitch": 75.76204192775172,
        "LShoulderRoll": 17.90519328209561,
        "LElbowRoll": 22.95977950425896,
        "LElbowYaw": 0
    },
    {
        "RShoulderPitch": 37.92491325573539,
        "RShoulderRoll": -18.64258587523276,
        "RElbowRoll": 24.167505427469536,
        "RElbowYaw": 0,
        "LShoulderPitch": 75.76204192775172,
        "LShoulderRoll": 17.90519328209561,
        "LElbowRoll": 22.95977950425896,
        "LElbowYaw": 0
    },
    {
        "RShoulderPitch": 37.92491325573539,
        "RShoulderRoll": -18.64258587523276,
        "RElbowRoll": 24.167505427469536,
        "RElbowYaw": 0,
        "LShoulderPitch": 75.76204192775172,
        "LShoulderRoll": 17.90519328209561,
        "LElbowRoll": 22.95977950425896,
        "LElbowYaw": 0
    },
    {
        "RShoulderPitch": 37.92491325573539,
        "RShoulderRoll": -18.64258587523276,
        "RElbowRoll": 24.167505427469536,
        "RElbowYaw": 0,
        "LShoulderPitch": 75.76204192775172,
        "LShoulderRoll": 17.90519328209561,
        "LElbowRoll": 22.95977950425896,
        "LElbowYaw": 0
    },
    {
        "RShoulderPitch": 71.2223078199066,
        "RShoulderRoll": -31.971840783832587,
        "RElbowRoll": 33.22942840722095,
        "RElbowYaw": 0,
        "LShoulderPitch": 76.06501722288128,
        "LShoulderRoll": 17.799440301270554,
        "LElbowRoll": 23.48918517954982,
        "LElbowYaw": -90
    },
    {
        "RShoulderPitch": 71.09546297205807,
        "RShoulderRoll": -30.017528586755166,
        "RElbowRoll": 31.797800522568252,
        "RElbowYaw": 0,
        "LShoulderPitch": 76.23288898944527,
        "LShoulderRoll": 17.72315713705185,
        "LElbowRoll": 23.52254556812042,
        "LElbowYaw": -90
    },
    {
        "RShoulderPitch": 71.90692468884903,
        "RShoulderRoll": -28.77407191889931,
        "RElbowRoll": 29.999174337684707,
        "RElbowYaw": 0,
        "LShoulderPitch": 76.40144832566159,
        "LShoulderRoll": 17.73062203858648,
        "LElbowRoll": 23.61669062957543,
        "LElbowYaw": -90
    },
    {
        "RShoulderPitch": 74.71994032993717,
        "RShoulderRoll": -27.315077125668704,
        "RElbowRoll": 30.374664689347526,
        "RElbowYaw": 0,
        "LShoulderPitch": 76.58486452865898,
        "LShoulderRoll": 17.570767476889397,
        "LElbowRoll": 23.557848798859993,
        "LElbowYaw": -90
    },
    {
        "RShoulderPitch": 77.65947697686114,
        "RShoulderRoll": -29.239736541214718,
        "RElbowRoll": 31.93310413891919,
        "RElbowYaw": 0,
        "LShoulderPitch": 76.78556927873557,
        "LShoulderRoll": 17.742548475251173,
        "LElbowRoll": 23.735561299308102,
        "LElbowYaw": -90
    },
    {
        "RShoulderPitch": 79.6897302654107,
        "RShoulderRoll": -30.057775080107092,
        "RElbowRoll": 31.990206301837077,
        "RElbowYaw": 0,
        "LShoulderPitch": 76.90442599465845,
        "LShoulderRoll": 17.6283497588245,
        "LElbowRoll": 23.705508087763803,
        "LElbowYaw": -90
    },
    {
        "RShoulderPitch": 80.18192089232508,
        "RShoulderRoll": -28.00221226592065,
        "RElbowRoll": 28.3631953940764,
        "RElbowYaw": 0,
        "LShoulderPitch": 77.07424342691615,
        "LShoulderRoll": 17.7057179840658,
        "LElbowRoll": 23.788573582972788,
        "LElbowYaw": -90
    },
    {
        "RShoulderPitch": 80.18192089232508,
        "RShoulderRoll": -28.00221226592065,
        "RElbowRoll": 28.3631953940764,
        "RElbowYaw": 0,
        "LShoulderPitch": 77.07424342691615,
        "LShoulderRoll": 17.7057179840658,
        "LElbowRoll": 23.788573582972788,
        "LElbowYaw": -90
    },
    {
        "RShoulderPitch": 82.25582302290027,
        "RShoulderRoll": -27.404165273610435,
        "RElbowRoll": 28.86805431663589,
        "RElbowYaw": 0,
        "LShoulderPitch": 77.23969039264105,
        "LShoulderRoll": 17.720123849323567,
        "LElbowRoll": 23.818210722007365,
        "LElbowYaw": -90
    },
    {
        "RShoulderPitch": 82.25582302290027,
        "RShoulderRoll": -27.404165273610435,
        "RElbowRoll": 28.86805431663589,
        "RElbowYaw": 0,
        "LShoulderPitch": 77.23969039264105,
        "LShoulderRoll": 17.720123849323567,
        "LElbowRoll": 23.818210722007365,
        "LElbowYaw": -90
    },
    {
        "RShoulderPitch": 82.25582302290027,
        "RShoulderRoll": -27.404165273610435,
        "RElbowRoll": 28.86805431663589,
        "RElbowYaw": 0,
        "LShoulderPitch": 77.23969039264105,
        "LShoulderRoll": 17.720123849323567,
        "LElbowRoll": 23.818210722007365,
        "LElbowYaw": -90
    },
    {
        "RShoulderPitch": 82.25582302290027,
        "RShoulderRoll": -27.404165273610435,
        "RElbowRoll": 28.86805431663589,
        "RElbowYaw": 0,
        "LShoulderPitch": 77.23969039264105,
        "LShoulderRoll": 17.720123849323567,
        "LElbowRoll": 23.818210722007365,
        "LElbowYaw": -90
    },
    {
        "RShoulderPitch": 84.8141693507627,
        "RShoulderRoll": -26.653643883508607,
        "RElbowRoll": 29.00696641896829,
        "RElbowYaw": 0,
        "LShoulderPitch": 77.72230672992538,
        "LShoulderRoll": 17.58689487827311,
        "LElbowRoll": 23.578070214107925,
        "LElbowYaw": -90
    },
    {
        "RShoulderPitch": 84.8141693507627,
        "RShoulderRoll": -26.653643883508607,
        "RElbowRoll": 29.00696641896829,
        "RElbowYaw": 0,
        "LShoulderPitch": 77.72230672992538,
        "LShoulderRoll": 17.58689487827311,
        "LElbowRoll": 23.578070214107925,
        "LElbowYaw": -90
    },
    {
        "RShoulderPitch": 85.72080997499188,
        "RShoulderRoll": -26.029870548011246,
        "RElbowRoll": 29.379718825929643,
        "RElbowYaw": 0,
        "LShoulderPitch": 78.18597443524327,
        "LShoulderRoll": 17.483065630983738,
        "LElbowRoll": 23.350010679767877,
        "LElbowYaw": -90
    },
    {
        "RShoulderPitch": 85.72080997499188,
        "RShoulderRoll": -26.029870548011246,
        "RElbowRoll": 29.379718825929643,
        "RElbowYaw": 0,
        "LShoulderPitch": 78.18597443524327,
        "LShoulderRoll": 17.483065630983738,
        "LElbowRoll": 23.350010679767877,
        "LElbowYaw": -90
    },
    {
        "RShoulderPitch": 85.72080997499188,
        "RShoulderRoll": -26.029870548011246,
        "RElbowRoll": 29.379718825929643,
        "RElbowYaw": 0,
        "LShoulderPitch": 78.18597443524327,
        "LShoulderRoll": 17.483065630983738,
        "LElbowRoll": 23.350010679767877,
        "LElbowYaw": -90
    },
    {
        "RShoulderPitch": 86.7036970159194,
        "RShoulderRoll": -26.069291264546244,
        "RElbowRoll": 30.189515881838815,
        "RElbowYaw": 0,
        "LShoulderPitch": 78.92365086851892,
        "LShoulderRoll": 17.456458608981134,
        "LElbowRoll": 23.267909954283283,
        "LElbowYaw": -90
    },
    {
        "RShoulderPitch": 86.7036970159194,
        "RShoulderRoll": -26.069291264546244,
        "RElbowRoll": 30.189515881838815,
        "RElbowYaw": 0,
        "LShoulderPitch": 78.92365086851892,
        "LShoulderRoll": 17.456458608981134,
        "LElbowRoll": 23.267909954283283,
        "LElbowYaw": -90
    },
    {
        "RShoulderPitch": 87.10824389909229,
        "RShoulderRoll": -25.97951201306751,
        "RElbowRoll": 30.394555758626183,
        "RElbowYaw": 0,
        "LShoulderPitch": 79.70102465799661,
        "LShoulderRoll": 17.200815155801667,
        "LElbowRoll": 23.458120980643997,
        "LElbowYaw": -90
    },
    {
        "RShoulderPitch": 87.10824389909229,
        "RShoulderRoll": -25.97951201306751,
        "RElbowRoll": 30.394555758626183,
        "RElbowYaw": 0,
        "LShoulderPitch": 79.70102465799661,
        "LShoulderRoll": 17.200815155801667,
        "LElbowRoll": 23.458120980643997,
        "LElbowYaw": -90
    },
    {
        "RShoulderPitch": 87.10824389909229,
        "RShoulderRoll": -25.97951201306751,
        "RElbowRoll": 30.394555758626183,
        "RElbowYaw": 0,
        "LShoulderPitch": 79.70102465799661,
        "LShoulderRoll": 17.200815155801667,
        "LElbowRoll": 23.458120980643997,
        "LElbowYaw": -90
    },
    {
        "RShoulderPitch": 87.10824389909229,
        "RShoulderRoll": -25.97951201306751,
        "RElbowRoll": 30.394555758626183,
        "RElbowYaw": 0,
        "LShoulderPitch": 79.70102465799661,
        "LShoulderRoll": 17.200815155801667,
        "LElbowRoll": 23.458120980643997,
        "LElbowYaw": -90
    },
    {
        "RShoulderPitch": 87.76767981503436,
        "RShoulderRoll": -26.031214436277793,
        "RElbowRoll": 30.54944849384077,
        "RElbowYaw": 0,
        "LShoulderPitch": 80.62435792568196,
        "LShoulderRoll": 17.150592076422,
        "LElbowRoll": 23.769034456358156,
        "LElbowYaw": -90
    },
    {
        "RShoulderPitch": 87.76767981503436,
        "RShoulderRoll": -26.031214436277793,
        "RElbowRoll": 30.54944849384077,
        "RElbowYaw": 0,
        "LShoulderPitch": 80.62435792568196,
        "LShoulderRoll": 17.150592076422,
        "LElbowRoll": 23.769034456358156,
        "LElbowYaw": -90
    },
    {
        "RShoulderPitch": 88.14831946088104,
        "RShoulderRoll": -25.72025636699112,
        "RElbowRoll": 30.57522336935503,
        "RElbowYaw": 0,
        "LShoulderPitch": 81.22004055658587,
        "LShoulderRoll": 17.126035946451925,
        "LElbowRoll": 23.942246529808813,
        "LElbowYaw": -90
    },
    {
        "RShoulderPitch": 88.20434329116326,
        "RShoulderRoll": -25.384922646379334,
        "RElbowRoll": 30.040856153602704,
        "RElbowYaw": 0,
        "LShoulderPitch": 81.33688082880718,
        "LShoulderRoll": 17.301231763110703,
        "LElbowRoll": 23.788040874640956,
        "LElbowYaw": -90
    },
    {
        "RShoulderPitch": 88.16944749223923,
        "RShoulderRoll": -25.07822908703015,
        "RElbowRoll": 29.586290504962307,
        "RElbowYaw": 0,
        "LShoulderPitch": 81.48662927031161,
        "LShoulderRoll": 17.467902579259853,
        "LElbowRoll": 23.846453182615534,
        "LElbowYaw": -90
    },
    {
        "RShoulderPitch": 88.16944749223923,
        "RShoulderRoll": -25.07822908703015,
        "RElbowRoll": 29.586290504962307,
        "RElbowYaw": 0,
        "LShoulderPitch": 81.48662927031161,
        "LShoulderRoll": 17.467902579259853,
        "LElbowRoll": 23.846453182615534,
        "LElbowYaw": -90
    },
    {
        "RShoulderPitch": 88.16944749223923,
        "RShoulderRoll": -25.07822908703015,
        "RElbowRoll": 29.586290504962307,
        "RElbowYaw": 0,
        "LShoulderPitch": 81.48662927031161,
        "LShoulderRoll": 17.467902579259853,
        "LElbowRoll": 23.846453182615534,
        "LElbowYaw": -90
    },
    {
        "RShoulderPitch": 88.11114555101537,
        "RShoulderRoll": -24.872496094767538,
        "RElbowRoll": 29.382023821143747,
        "RElbowYaw": 0,
        "LShoulderPitch": 81.47757821560323,
        "LShoulderRoll": 17.661910273279087,
        "LElbowRoll": 23.624776055332546,
        "LElbowYaw": -90
    }
]